Workbook

Sheet Dashboard
D2: Budget vs. Actual Dashboard
D4: Current Month -> | F4: April
D6: Figures in INR | F6: Budget | G6: Actual | I6: Var.Abs. | J6: Var.% | L6: Budget vs. Actual Income | R6: Budget vs. Actual Expense
D7: Income:
D8: Base Salary | F8: =INDEX(Data!$D$4:$P$18,MATCH(Dashboard!D8,Data!$D$4:$D$18,0),MATCH(Dashboard!$F$4,Data!$D$4:$P$4,0)) -> 35000 | G8: =INDEX(Data!$D$25:$P$39,MATCH(Dashboard!D8,Data!$D$25:$D$39,0),MATCH(Dashboard!$F$4,Data!$D$25:$P$25,0)) -> 35000 | I8: =G8-F8 -> 0 | J8: =G8/F8-1 -> 0
D9: Bonus | F9: =INDEX(Data!$D$4:$P$18,MATCH(Dashboard!D9,Data!$D$4:$D$18,0),MATCH(Dashboard!$F$4,Data!$D$4:$P$4,0)) -> 5000 | G9: =INDEX(Data!$D$25:$P$39,MATCH(Dashboard!D9,Data!$D$25:$D$39,0),MATCH(Dashboard!$F$4,Data!$D$25:$P$25,0)) -> 4000 | I9: =G9-F9 -> -1000 | J9: =G9/F9-1 -> -0.2
D10: Side Hustle | F10: =INDEX(Data!$D$4:$P$18,MATCH(Dashboard!D10,Data!$D$4:$D$18,0),MATCH(Dashboard!$F$4,Data!$D$4:$P$4,0)) -> 2500 | G10: =INDEX(Data!$D$25:$P$39,MATCH(Dashboard!D10,Data!$D$25:$D$39,0),MATCH(Dashboard!$F$4,Data!$D$25:$P$25,0)) -> 2462 | I10: =G10-F10 -> -38 | J10: =G10/F10-1 -> -0.0152
D11: Total Income | F11: =SUM(F8:F10) -> 42500 | G11: =SUM(G8:G10) -> 41462 | I11: =G11-F11 -> -1038 | J11: =G11/F11-1 -> -0.024423529
D13: Expenses:
D14: Rent | F14: =INDEX(Data!$D$4:$P$18,MATCH(Dashboard!D14,Data!$D$4:$D$18,0),MATCH(Dashboard!$F$4,Data!$D$4:$P$4,0)) -> 12000 | G14: =INDEX(Data!$D$25:$P$39,MATCH(Dashboard!D14,Data!$D$25:$D$39,0),MATCH(Dashboard!$F$4,Data!$D$25:$P$25,0)) -> 11500 | I14: =F14-G14 -> 500 | J14: =F14/G14-1 -> 0.043478261
D15: Utilities | F15: =INDEX(Data!$D$4:$P$18,MATCH(Dashboard!D15,Data!$D$4:$D$18,0),MATCH(Dashboard!$F$4,Data!$D$4:$P$4,0)) -> 4340 | G15: =INDEX(Data!$D$25:$P$39,MATCH(Dashboard!D15,Data!$D$25:$D$39,0),MATCH(Dashboard!$F$4,Data!$D$25:$P$25,0)) -> 4586 | I15: =F15-G15 -> -246 | J15: =F15/G15-1 -> -0.053641518
D16: Transport | F16: =INDEX(Data!$D$4:$P$18,MATCH(Dashboard!D16,Data!$D$4:$D$18,0),MATCH(Dashboard!$F$4,Data!$D$4:$P$4,0)) -> 7080 | G16: =INDEX(Data!$D$25:$P$39,MATCH(Dashboard!D16,Data!$D$25:$D$39,0),MATCH(Dashboard!$F$4,Data!$D$25:$P$25,0)) -> 7076 | I16: =F16-G16 -> 4 | J16: =F16/G16-1 -> 0.00056529112
D17: Groceries | F17: =INDEX(Data!$D$4:$P$18,MATCH(Dashboard!D17,Data!$D$4:$D$18,0),MATCH(Dashboard!$F$4,Data!$D$4:$P$4,0)) -> 4200 | G17: =INDEX(Data!$D$25:$P$39,MATCH(Dashboard!D17,Data!$D$25:$D$39,0),MATCH(Dashboard!$F$4,Data!$D$25:$P$25,0)) -> 3955 | I17: =F17-G17 -> 245 | J17: =F17/G17-1 -> 0.061946903
D18: Leisure | F18: =INDEX(Data!$D$4:$P$18,MATCH(Dashboard!D18,Data!$D$4:$D$18,0),MATCH(Dashboard!$F$4,Data!$D$4:$P$4,0)) -> 9000 | G18: =INDEX(Data!$D$25:$P$39,MATCH(Dashboard!D18,Data!$D$25:$D$39,0),MATCH(Dashboard!$F$4,Data!$D$25:$P$25,0)) -> 8536 | I18: =F18-G18 -> 464 | J18: =F18/G18-1 -> 0.054358013
D19: Other | F19: =INDEX(Data!$D$4:$P$18,MATCH(Dashboard!D19,Data!$D$4:$D$18,0),MATCH(Dashboard!$F$4,Data!$D$4:$P$4,0)) -> 4200 | G19: =INDEX(Data!$D$25:$P$39,MATCH(Dashboard!D19,Data!$D$25:$D$39,0),MATCH(Dashboard!$F$4,Data!$D$25:$P$25,0)) -> 5107 | I19: =F19-G19 -> -907 | J19: =F19/G19-1 -> -0.17759937
D20: Total Expenses | F20: =SUM(F14:F19) -> 40820 | G20: =SUM(G14:G19) -> 40760 | I20: =F20-G20 -> 60 | J20: =F20/G20-1 -> 0.0014720314
D22: Savings | F22: =F11-F20 -> 1680 | G22: =G11-G20 -> 702 | I22: =G22-F22 -> -978 | J22: =G22/F22-1 -> -0.58214286

Sheet Data
D2: Budgeted Income & Expenses for the year 2025
D4: Items | E4: January | F4: February | G4: March | H4: April | I4: May | J4: June | K4: July | L4: August | M4: September | N4: October | O4: November | P4: December
D5: Income:
D6: Base Salary | E6: 35000 | F6: 35000 | G6: 35000 | H6: 35000 | I6: 35000 | J6: 35000 | K6: 38000 | L6: 38000 | M6: 38000 | N6: 38000 | O6: 38000 | P6: 38000
D7: Bonus | E7: 5000 | F7: 5000 | G7: 5000 | H7: 5000 | I7: 5000 | J7: 5000 | K7: 5000 | L7: 5000 | M7: 5000 | N7: 5000 | O7: 5000 | P7: 5000
D8: Side Hustle | E8: 2500 | F8: 2500 | G8: 2500 | H8: 2500 | I8: 2500 | J8: 2500 | K8: 2500 | L8: 2500 | M8: 2500 | N8: 2500 | O8: 2500 | P8: 2500
D9: Total Income | E9: =SUM(E6:E8) -> 42500 | F9: =SUM(F6:F8) -> 42500 | G9: =SUM(G6:G8) -> 42500 | H9: =SUM(H6:H8) -> 42500 | I9: =SUM(I6:I8) -> 42500 | J9: =SUM(J6:J8) -> 42500 | K9: =SUM(K6:K8) -> 45500 | L9: =SUM(L6:L8) -> 45500 | ... P9: =SUM(P6:P8) -> 45500
D11: Expenses:
D12: Rent | E12: 12000 | F12: 12000 | G12: 12000 | H12: 12000 | I12: 12000 | J12: 12000 | K12: 12000 | L12: 12000 | M12: 12000 | N12: 12000 | O12: 12000 | P12: 12000
D13: Utilities | E13: 4400 | F13: 4050 | G13: 4230 | H13: 4340 | I13: 4200 | J13: 4260 | K13: 4480 | L13: 4500 | M13: 4450 | N13: 4300 | O13: 4050 | P13: 4300
D14: Transport | E14: 6500 | F14: 6900 | G14: 6600 | H14: 7080 | I14: 7040 | J14: 7200 | K14: 7150 | L14: 6600 | M14: 7250 | N14: 6750 | O14: 6800 | P14: 6900
D15: Groceries | E15: 3800 | F15: 3600 | G15: 4300 | H15: 4200 | I15: 4500 | J15: 3800 | K15: 3950 | L15: 4150 | M15: 3700 | N15: 3700 | O15: 3600 | P15: 4500
D16: Leisure | E16: 8100 | F16: 8500 | G16: 9200 | H16: 9000 | I16: 9800 | J16: 9600 | K16: 8700 | L16: 8700 | M16: 10000 | N16: 8000 | O16: 10300 | P16: 9700
D17: Other | E17: 4200 | F17: 4200 | G17: 4200 | H17: 4200 | I17: 4200 | J17: 4200 | K17: 5500 | L17: 5500 | M17: 5500 | N17: 5500 | O17: 5500 | P17: 5500
D18: Total Expenses | E18: =SUM(E12:E17) -> 39000 | F18: =SUM(F12:F17) -> 39250 | G18: =SUM(G12:G17) -> 40530 | H18: =SUM(H12:H17) -> 40820 | I18: =SUM(I12:I17) -> 41740 | J18: =SUM(J12:J17) -> 41060 | K18: =SUM(K12:K17) -> 41780 | L18: =SUM(L12:L17) -> 41450 | ... P18: =SUM(P12:P17) -> 42900
D20: Savings | E20: =IF(E9>E18,E9-E18,0) -> 3500 | F20: =IF(F9>F18,F9-F18,0) -> 3250 | G20: =IF(G9>G18,G9-G18,0) -> 1970 | H20: =IF(H9>H18,H9-H18,0) -> 1680 | I20: =IF(I9>I18,I9-I18,0) -> 760 | J20: =IF(J9>J18,J9-J18,0) -> 1440 | K20: =IF(K9>K18,K9-K18,0) -> 3720 | L20: =IF(L9>L18,L9-L18,0) -> 4050 | ... P20: =IF(P9>P18,P9-P18,0) -> 2600
D21: Cumulative Savings | E21: =E20 -> 3500 | F21: =IF(F20>0,E21+F20,E21+F20+F9-F18) -> 6750 | G21: =IF(G20>0,F21+G20,F21+G20+G9-G18) -> 8720 | H21: =IF(H20>0,G21+H20,G21+H20+H9-H18) -> 10400 | I21: =IF(I20>0,H21+I20,H21+I20+I9-I18) -> 11160 | J21: =IF(J20>0,I21+J20,I21+J20+J9-J18) -> 12600 | K21: =IF(K20>0,J21+K20,J21+K20+K9-K18) -> 16320 | L21: =IF(L20>0,K21+L20,K21+L20+L9-L18) -> 20370 | M21: =IF(M20>0,L21+M20,L21+M20+M9-M18) -> 22970 | ... P21: =IF(P20>0,O21+P20,O21+P20+P9-P18) -> 34070
D23: Acutal Income & Expenses for the year 2025
D25: Items | E25: January | F25: February | G25: March | H25: April | I25: May | J25: June | K25: July | L25: August | M25: September | N25: October | O25: November | P25: December
D26: Income:
D27: Base Salary | E27: 35000 | F27: 35000 | G27: 35000 | H27: 35000 | I27: 35000 | J27: 35000 | K27: 35000 | L27: 35000 | M27: 35000 | N27: 35000 | O27: 35000 | P27: 35000
D28: Bonus | E28: 4000 | F28: 4000 | G28: 4000 | H28: 4000 | I28: 4000 | J28: 4000 | K28: 4500 | L28: 4500 | M28: 4500 | N28: 4500 | O28: 4500 | P28: 4500
D29: Side Hustle | E29: 2800 | F29: 2186 | G29: 2508 | H29: 2462 | I29: 2515 | J29: 2515 | K29: 2024 | L29: 2298 | M29: 2106 | N29: 2748 | O29: 2565 | P29: 2321
D30: Total Income | E30: =SUM(E27:E29) -> 41800 | F30: =SUM(F27:F29) -> 41186 | G30: =SUM(G27:G29) -> 41508 | H30: =SUM(H27:H29) -> 41462 | I30: =SUM(I27:I29) -> 41515 | J30: =SUM(J27:J29) -> 41515 | K30: =SUM(K27:K29) -> 41524 | L30: =SUM(L27:L29) -> 41798 | ... P30: =SUM(P27:P29) -> 41821
D32: Expenses:
D33: Rent | E33: 11500 | F33: 11500 | G33: 11500 | H33: 11500 | I33: 11500 | J33: 11500 | K33: 12000 | L33: 12000 | M33: 12000 | N33: 12000 | O33: 12000 | P33: 12000
D34: Utilities | E34: 4407 | F34: 4305 | G34: 4559 | H34: 4586 | I34: 4454 | J34: 4788 | K34: 4261 | L34: 4675 | M34: 4525 | N34: 4795 | O34: 4390 | P34: 4338
D35: Transport | E35: 7150 | F35: 6778 | G35: 6148 | H35: 7076 | I35: 7372 | J35: 6845 | K35: 6685 | L35: 6343 | M35: 6956 | N35: 7404 | O35: 7600 | P35: 6502
D36: Groceries | E36: 3736 | F36: 4051 | G36: 3499 | H36: 3955 | I36: 4387 | J36: 3712 | K36: 3680 | L36: 4483 | M36: 4264 | N36: 3358 | O36: 3300 | P36: 3266
D37: Leisure | E37: 10054 | F37: 8610 | G37: 8946 | H37: 8536 | I37: 9705 | J37: 9257 | K37: 8122 | L37: 8157 | M37: 10339 | N37: 8427 | O37: 8824 | P37: 9159
D38: Other | E38: 4735 | F38: 5482 | G38: 5178 | H38: 5107 | I38: 5266 | J38: 5375 | K38: 4685 | L38: 5278 | M38: 5019 | N38: 5046 | O38: 5355 | P38: 5346
D39: Total Expenses | E39: =SUM(E33:E38) -> 41582 | F39: =SUM(F33:F38) -> 40726 | G39: =SUM(G33:G38) -> 39830 | H39: =SUM(H33:H38) -> 40760 | I39: =SUM(I33:I38) -> 42684 | J39: =SUM(J33:J38) -> 41477 | K39: =SUM(K33:K38) -> 39433 | L39: =SUM(L33:L38) -> 40936 | ... P39: =SUM(P33:P38) -> 40611
D41: Savings | E41: =IF(E30>E39,E30-E39,0) -> 218 | F41: =IF(F30>F39,F30-F39,0) -> 460 | G41: =IF(G30>G39,G30-G39,0) -> 1678 | H41: =IF(H30>H39,H30-H39,0) -> 702 | I41: =IF(I30>I39,I30-I39,0) -> 0 | J41: =IF(J30>J39,J30-J39,0) -> 38 | K41: =IF(K30>K39,K30-K39,0) -> 2091 | L41: =IF(L30>L39,L30-L39,0) -> 862 | ... P41: =IF(P30>P39,P30-P39,0) -> 1210
D42: Cumulative Savings | E42: =E41 -> 218 | F42: =IF(F41>0,E42+F41,E42+F41+F30-F39) -> 678 | G42: =IF(G41>0,F42+G41,F42+G41+G30-G39) -> 2356 | H42: =IF(H41>0,G42+H41,G42+H41+H30-H39) -> 3058 | I42: =IF(I41>0,H42+I41,H42+I41+I30-I39) -> 1889 | J42: =IF(J41>0,I42+J41,I42+J41+J30-J39) -> 1927 | K42: =IF(K41>0,J42+K41,J42+K41+K30-K39) -> 4018 | L42: =IF(L41>0,K42+L41,K42+L41+L30-L39) -> 4880 | M42: =IF(M41>0,L42+M41,L42+M41+M30-M39) -> 3383 | ... P42: =IF(P41>0,O42+P41,O42+P41+P30-P39) -> 6407
