Workbook
Name BS: Statements!$B$55
Name CF: Statements!$B$103
Name days: Dashboard!$G$18
Name Debt: Schedule!$B$86
Name EF: Assumptions!$B$83
Name Equity: Schedule!$B$112
Name IS: Statements!$B$20
Name PPE: Schedule!$B$13
Name RE: Schedule!$B$112
Name RF: Assumptions!$B$18
Name tax_rate: FCFF!$E$14
Name terminal_growth: FCFF!$E$16
Name wacc: FCFF!$E$15
Name WC: Schedule!$B$63

Sheet Dashboard
B2: Denny's Diner
B3: Dashboard
B4: (In $ thousands, except per share amounts)
B7: Model Assumption | F7: Units:
B9: Company Name | G9: =B2 -> Denny's Diner | M9: Cell Reference
B10: Ticker | G10: DENN
B11: Last Historical | F11: Date | G11: =Statements!I7 -> 45651 | L11: Hardcode | N11: Caution
L12: Calculation | N12: Assumptions
B13: Selected Scenario | G13: Street | L13: Reference | N13: Notes
L14: (Except for the dashboard, and others)
B15: Model Start Date | F15: Date | G15: =Statements!I7 -> 45651
B16: Model End Date | F16: Date | G16: =Statements!N7 -> 47477
B17: No. of Years Projected | F17: Years | G17: =YEARFRAC(G15,G16,1) -> 4.9981752
B18: Days in an Year | F18: Days | G18: 365
C21: Table of Contents
C22: Particulars
B24: 1 | C24: Dashboard
B25: 2 | C25: Financials
B26: 3 | C26: Statements
B27: 4 | C27: Scenario
B28: 5 | C28: Assumptions
B29: 6 | C29: Schedule
B30: 7 | C30: Valuation
B31: 8 | C31: Beta
B32: 9 | C32: WACC
B33: 10 | C33: FCFF
B34: 11 | C34: Report
B35: 12 | C35: Ratio Analysis
B36: 13 | C36: Equity Report

Sheet Financials->

Sheet Statements
B2: =Dashboard!B2 -> Denny's Diner
B3: Financial statements
B4: =Dashboard!B4 -> (In $ thousands, except per share amounts)
B5: Active Scenario | D5: =Dashboard!G13 -> Street
B6: Historicals / Forecast | G6: Historicals | J6: Forecast | O6: CAGR | Q6: Notes
B7: Month / Year (A/E) | G7: 44920 | H7: =EDATE(G7,12) -> 45285 | I7: =EDATE(H7,12) -> 45651 | J7: =EDATE(I7,12) -> 46016 | K7: =EDATE(J7,12) -> 46381 | L7: =EDATE(K7,12) -> 46746 | M7: =EDATE(L7,12) -> 47112 | N7: =EDATE(M7,12) -> 47477 | O7: 22A - 25A | P7: 25A - 30E
B9: <-Back to dashboard
B11: Go to -> | C11: Income statement | E11: Balance statement
B15: Templete: | C15: Standard | E15: Source: | F15: Company Website
B16: Period type: | C16: Annual | E16: Decimals: | F16: Default
B17: Currency: | C17: Reported
B18: Units: | C18: USD
A20: # | B20: Income statement | G20: 44920 | H20: 45285 | I20: 45651 | J20: 46016 | K20: 46381 | L20: 46746 | M20: 47112 | N20: 47477
B22: Revenue:
B23: Company restaurant sales | G23: 199753 | H23: 215532 | I23: 211781 | J23: =Assumptions!J23 -> 213633.92 | K23: =Assumptions!K23 -> 218849.96 | L23: =Assumptions!L23 -> 228203.92 | M23: =Assumptions!M23 -> 238731.34 | N23: =Assumptions!N23 -> 251341.8
B24: Franchise and license revenue | G24: 256676 | H24: 248390 | I24: 240553 | J24: =Assumptions!J42 -> 241068.35 | K24: =Assumptions!K42 -> 245424.28 | L24: =Assumptions!L42 -> 254555.12 | M24: =Assumptions!M42 -> 264671.25 | N24: =Assumptions!N42 -> 276654.6
B25: Total operating revenue | G25: 456429 | H25: 463922 | I25: =SUM(I23:I24) -> 452334 | J25: =SUM(J23:J24) -> 454702.27 | K25: =SUM(K23:K24) -> 464274.24 | L25: =SUM(L23:L24) -> 482759.04 | M25: =SUM(M23:M24) -> 503402.59 | N25: =SUM(N23:N24) -> 527996.41
B26: Costs of company restaurant sales:
B27: Product costs | G27: 53617 | H27: 55789 | I27: 53931 | J27: =Assumptions!J86 -> 55718.533 | K27: =Assumptions!K86 -> 57048.894 | L27: =Assumptions!L86 -> 60191.558 | M27: =Assumptions!M86 -> 63708.953 | N27: =Assumptions!N86 -> 67525.477
B28: Payroll and benefits | G28: 76412 | H28: 80666 | I28: 80605 | J28: =Assumptions!J94 -> 81242.611 | K28: =Assumptions!K94 -> 84511.78 | L28: =Assumptions!L94 -> 91198.44 | M28: =Assumptions!M94 -> 98937.055 | N28: =Assumptions!N94 -> 108511.31
B29: Occupancy | G29: 15154 | H29: 16809 | I29: 18129 | J29: =Assumptions!J104 -> 15545.869 | K29: =Assumptions!K104 -> 16637.873 | L29: =Assumptions!L104 -> 17517.315 | M29: =Assumptions!M104 -> 17640.413 | N29: =Assumptions!N104 -> 18622.843
B30: Other operating expenses | G30: 34275 | H30: 34335 | I30: 37079 | J30: =Assumptions!J107 -> 35023.704 | K30: =Assumptions!K107 -> 36059.944 | L30: =Assumptions!L107 -> 38084.487 | M30: =Assumptions!M107 -> 39195.646 | N30: =Assumptions!N107 -> 41257.666
B31: Total costs of company restaurant sales | G31: =SUM(G27:G30) -> 179458 | H31: =SUM(H27:H30) -> 187599 | I31: =SUM(I27:I30) -> 189744 | J31: =SUM(J27:J30) -> 187530.72 | K31: =SUM(K27:K30) -> 194258.49 | L31: =SUM(L27:L30) -> 206991.8 | M31: =SUM(M27:M30) -> 219482.07 | N31: =SUM(N27:N30) -> 235917.29
B33: Costs of franchise and license revenue | G33: 135327 | H33: 122452 | I33: 120226 | J33: =Assumptions!J119 -> 122250.35 | K33: =Assumptions!K119 -> 122584.66 | L33: =Assumptions!L119 -> 128099.44 | M33: =Assumptions!M119 -> 133401.97 | N33: =Assumptions!N119 -> 138979.76
B34: General and administrative expenses | G34: 67173 | H34: 77770 | I34: 80197 | J34: =Assumptions!J121 -> 74586.733 | K34: =Assumptions!K121 -> 78766.623 | L34: =Assumptions!L121 -> 82227.636 | M34: =Assumptions!M121 -> 84574.678 | N34: =Assumptions!N121 -> 89405.624
B35: Depreciation and amortization | G35: 14862 | H35: 14385 | I35: 14857 | J35: =Schedule!J27+Schedule!J45+Schedule!J60 -> 13724.577 | K35: =Schedule!K27+Schedule!K45+Schedule!K60 -> 13914.684 | L35: =Schedule!L27+Schedule!L45+Schedule!L60 -> 14602.521 | M35: =Schedule!M27+Schedule!M45+Schedule!M60 -> 15365.381 | N35: =Schedule!N27+Schedule!N45+Schedule!N60 -> 16163.077
B36: Goodwill impairment charges | G36: 0 | H36: 6363 | I36: 20 | J36: 0 | K36: 0 | L36: 0 | M36: 0 | N36: 0
B37: Operating (gains), losses and other charges, net | G37: -1005 | H37: 2530 | I37: 1974 | J37: 0 | K37: 0 | L37: 0 | M37: 0 | N37: 0
B38: Total operating costs and expenses, net | G38: 395815 | H38: 411099 | I38: 407018 | J38: =SUM(J33:J37)+J31 -> 398092.38 | K38: =SUM(K33:K37)+K31 -> 409524.46 | L38: =SUM(L33:L37)+L31 -> 431921.39 | M38: =SUM(M33:M37)+M31 -> 452824.1 | N38: =SUM(N33:N37)+N31 -> 480465.75
B40: Operating income | G40: 60614 | H40: 52823 | I40: 45316 | J40: =J25-J38 -> 56609.888 | K40: =K25-K38 -> 54749.777 | L40: =L25-L38 -> 50837.643 | M40: =M25-M38 -> 50578.488 | N40: =N25-N38 -> 47530.66
B41: Interest expense, net | G41: 13769 | H41: 17597 | I41: 17974 | J41: =Schedule!J95+Schedule!J110 -> 16021.14 | K41: =Schedule!K95+Schedule!K110 -> 12912.75 | L41: =Schedule!L95+Schedule!L110 -> 9910.15 | M41: =Schedule!M95+Schedule!M110 -> 7234.5 | N41: =Schedule!N95+Schedule!N110 -> 4563.2
B42: Other nonoperating income, net | G42: -52585 | H42: 8288 | I42: -1907 | J42: 0 | K42: 0 | L42: 0 | M42: 0 | N42: 0
B43: Net income before income taxes | G43: 99430 | H43: 26938 | I43: 29249 | J43: =J40-SUM(J41:J42) -> 40588.748 | K43: =K40-SUM(K41:K42) -> 41837.027 | L43: =L40-SUM(L41:L42) -> 40927.493 | M43: =M40-SUM(M41:M42) -> 43343.988 | N43: =N40-SUM(N41:N42) -> 42967.46
B44: Provision for income taxes | G44: 24718 | H44: 6993 | I44: 7678 | J44: =Assumptions!J124 -> 10553.074 | K44: =Assumptions!K124 -> 10877.627 | L44: =Assumptions!L124 -> 10641.148 | M44: =Assumptions!M124 -> 11269.437 | N44: =Assumptions!N124 -> 11171.54
B45: Net income | G45: 74712 | H45: 19945 | I45: 21571 | J45: =J43-J44 -> 30035.673 | K45: =K43-K44 -> 30959.4 | L45: =L43-L44 -> 30286.345 | M45: =M43-M44 -> 32074.551 | N45: =N43-N44 -> 31795.921
B47: Earnings per Share
B48: Basic | G48: =G$45/G52 -> 1.2294022 | H48: =H$45/H52 -> 0.3562625 | I48: =I$45/I52 -> 0.41088402 | J48: =J$45/J52 -> 0.57211896 | K48: =K$45/K52 -> 0.58971409 | L48: =L$45/L52 -> 0.57689375 | M48: =M$45/M52 -> 0.61095547 | N48: =N$45/N52 -> 0.60564812
B49: Diluted | G49: =G$45/G53 -> 1.2272212 | H49: =H$45/H53 -> 0.3549185 | I49: =I$45/I53 -> 0.40998594 | J49: =J$45/J53 -> 0.57086846 | K49: =K$45/K53 -> 0.58842514 | L49: =L$45/L53 -> 0.57563282 | M49: =M$45/M53 -> 0.60962009 | N49: =N$45/N53 -> 0.60432434
B51: Weighted Average Shares Outstanding
B52: Basic | G52: 60771 | H52: 55984 | I52: 52499 | J52: =I52 -> 52499 | K52: =J52 -> 52499 | L52: =K52 -> 52499 | M52: =L52 -> 52499 | N52: =M52 -> 52499
B53: Diluted | G53: 60879 | H53: 56196 | I53: 52614 | J53: =I53 -> 52614 | K53: =J53 -> 52614 | L53: =K53 -> 52614 | M53: =L53 -> 52614 | N53: =M53 -> 52614
A55: # | B55: Balance sheet | G55: 44920 | H55: 45285 | I55: 45651 | J55: 46016 | K55: 46381 | L55: 46746 | M55: 47112 | N55: 47477
B57: Assets
B58: Current assets:
B59: Cash and cash equivalents | G59: 3523 | H59: 4893 | I59: 1698 | J59: =J135 -> 2265.5068 | K59: =K135 -> 8146.7722 | L59: =L135 -> 9126.4641 | M59: =M135 -> 14570.65 | N59: =N135 -> 17404.289
B60: Investments | G60: 1746 | H60: 1281 | I60: 1106 | J60: =I60 -> 1106 | K60: =J60 -> 1106 | L60: =K60 -> 1106 | M60: =L60 -> 1106 | N60: =M60 -> 1106
B61: Receivables, net | G61: 25576 | H61: 21391 | I61: 24433 | J61: =Schedule!J66 -> 24560.923 | K61: =Schedule!K66 -> 25077.957 | L61: =Schedule!L66 -> 26076.42 | M61: =Schedule!M66 -> 27191.49 | N61: =Schedule!N66 -> 28519.935
B62: Inventories | G62: 5538 | H62: 2175 | I62: 1747 | J62: =Schedule!J67 -> 1726.622 | K62: =Schedule!K67 -> 1788.5656 | L62: =Schedule!L67 -> 1905.8029 | M62: =Schedule!M67 -> 2020.8026 | N62: =Schedule!N67 -> 2172.1241
B63: Assets held for sale | G63: 1403 | H63: 1455 | I63: 381 | J63: =I63 -> 381 | K63: =J63 -> 381 | L63: =K63 -> 381 | M63: =L63 -> 381 | N63: =M63 -> 381
B64: Prepaid and other current assets | G64: 12529 | H64: 12855 | I64: 10628 | J64: =Schedule!J77 -> 11921.591 | K64: =Schedule!K77 -> 11981.953 | L64: =Schedule!L77 -> 12153.023 | M64: =Schedule!M77 -> 12954.306 | N64: =Schedule!N77 -> 13501.838
B65: Total current assets | G65: =SUM(G59:G64) -> 50315 | H65: =SUM(H59:H64) -> 44050 | I65: =SUM(I59:I64) -> 39993 | J65: =SUM(J59:J64) -> 41961.642 | K65: =SUM(K59:K64) -> 48482.248 | L65: =SUM(L59:L64) -> 50748.71 | M65: =SUM(M59:M64) -> 58224.249 | N65: =SUM(N59:N64) -> 63085.186
B66: Property, net of accumulated depreciation | G66: 94469 | H66: 93494 | I66: 111417 | J66: =Schedule!J22 -> 104104.34 | K66: =Schedule!K22 -> 99340.177 | L66: =Schedule!L22 -> 95771.74 | M66: =Schedule!M22 -> 94240.268 | N66: =Schedule!N22 -> 94096.945
B67: Financing lease right-of-use assets, net | G67: 6499 | H67: 6098 | I67: 6200 | J67: =I67 -> 6200 | K67: =J67 -> 6200 | L67: =K67 -> 6200 | M67: =L67 -> 6200 | N67: =M67 -> 6200
B68: Operating lease right-of-use assets, net | G68: 126065 | H68: 116795 | I68: 124738 | J68: =I68 -> 124738 | K68: =J68 -> 124738 | L68: =K68 -> 124738 | M68: =L68 -> 124738 | N68: =M68 -> 124738
B69: Goodwill | G69: 72740 | H69: 65908 | I69: 66357 | J69: =I69 -> 66357 | K69: =J69 -> 66357 | L69: =K69 -> 66357 | M69: =L69 -> 66357 | N69: =M69 -> 66357
B70: Intangible assets, net | G70: 95034 | H70: 93428 | I70: 91739 | J70: =Schedule!J40 -> 91669.663 | K70: =Schedule!K40 -> 91205.684 | L70: =Schedule!L40 -> 90708.534 | M70: =Schedule!M40 -> 90049.051 | N70: =Schedule!N40 -> 89134.02
B71: Deferred financing costs, net | G71: 2337 | H71: 1702 | I71: 1066 | J71: =I71 -> 1066 | K71: =J71 -> 1066 | L71: =K71 -> 1066 | M71: =L71 -> 1066 | N71: =M71 -> 1066
B72: Other noncurrent assets | G72: 50876 | H72: 43343 | I72: 54764 | J72: =Schedule!J83 -> 49405.293 | K72: =Schedule!K83 -> 50010.28 | L72: =Schedule!L83 -> 54300.914 | M72: =Schedule!M83 -> 55181.589 | N72: =Schedule!N83 -> 58046.991
B73: Total assets | G73: =SUM(G66:G72)+G65 -> 498335 | H73: =SUM(H66:H72)+H65 -> 464818 | I73: =SUM(I66:I72)+I65 -> 496274 | J73: =SUM(J66:J72)+J65 -> 485501.93 | K73: =SUM(K66:K72)+K65 -> 487399.39 | L73: =SUM(L66:L72)+L65 -> 489890.9 | M73: =SUM(M66:M72)+M65 -> 496056.16 | N73: =SUM(N66:N72)+N65 -> 502724.14
B75: Liabilities
B76: Current liabilities:
B77: Current finance lease liabilities | G77: 1683 | H77: 1383 | I77: 1284 | J77: =I77 -> 1284 | K77: =J77 -> 1284 | L77: =K77 -> 1284 | M77: =L77 -> 1284 | N77: =M77 -> 1284
B78: Current operating lease liabilities | G78: 15310 | H78: 14779 | I78: 15487 | J78: =I78 -> 15487 | K78: =J78 -> 15487 | L78: =K78 -> 15487 | M78: =L78 -> 15487 | N78: =M78 -> 15487
B79: Accounts payable | G79: 19896 | H79: 24070 | I79: 19985 | J79: =Schedule!J70 -> 19751.883 | K79: =Schedule!K70 -> 20460.494 | L79: =Schedule!L70 -> 21801.644 | M79: =Schedule!M70 -> 23117.195 | N79: =Schedule!N70 -> 24848.254
B80: Other current liabilities | G80: 56762 | H80: 63068 | I80: 58842 | J80: =Schedule!J79 -> 59170.653 | K80: =Schedule!K79 -> 61309.131 | L80: =Schedule!L79 -> 63123.888 | M80: =Schedule!M79 -> 65935.798 | N80: =Schedule!N79 -> 69306.65
B81: Total current liabilities | G81: =SUM(G77:G80) -> 93651 | H81: =SUM(H77:H80) -> 103300 | I81: =SUM(I77:I80) -> 95598 | J81: =SUM(J77:J80) -> 95693.536 | K81: =SUM(K77:K80) -> 98540.625 | L81: =SUM(L77:L80) -> 101696.53 | M81: =SUM(M77:M80) -> 105823.99 | N81: =SUM(N77:N80) -> 110925.9
B82: Revolver | G82: 0 | H82: 0 | I82: 0 | J82: =Schedule!J107 -> 0 | K82: =Schedule!K107 -> 0 | L82: =Schedule!L107 -> 0 | M82: =Schedule!M107 -> 0 | N82: =Schedule!N107 -> 0
B83: Long-term debt | G83: 261500 | H83: 255500 | I83: 261300 | J83: =Schedule!J91 -> 211300 | K83: =Schedule!K91 -> 171300 | L83: =Schedule!L91 -> 131300 | M83: =Schedule!M91 -> 91300 | N83: =Schedule!N91 -> 51300
B84: Noncurrent finance lease liabilities | G84: 9555 | H84: 9150 | I84: 9284 | J84: =I84 -> 9284 | K84: =J84 -> 9284 | L84: =K84 -> 9284 | M84: =L84 -> 9284 | N84: =M84 -> 9284
B85: Noncurrent operating lease liabilities | G85: 123404 | H85: 114451 | I85: 120841 | J85: =I85 -> 120841 | K85: =J85 -> 120841 | L85: =K85 -> 120841 | M85: =L85 -> 120841 | N85: =M85 -> 120841
B86: Liability for insurance claims, less current portion | G86: 7324 | H86: 6929 | I86: 5866 | J86: =I86 -> 5866 | K86: =J86 -> 5866 | L86: =K86 -> 5866 | M86: =L86 -> 5866 | N86: =M86 -> 5866
B87: Deferred income taxes, net | G87: 7419 | H87: 6582 | I87: 9964 | J87: =I87 -> 9964 | K87: =J87 -> 9964 | L87: =K87 -> 9964 | M87: =L87 -> 9964 | N87: =M87 -> 9964
B88: Other noncurrent liabilities | G88: 32598 | H88: 31592 | I88: 27446 | J88: =Schedule!J81 -> 30342.844 | K88: =Schedule!K81 -> 30256.024 | L88: =Schedule!L81 -> 30989.279 | M88: =Schedule!M81 -> 32904.355 | N88: =Schedule!N81 -> 34271.253
B89: Total long-term liabilities | G89: =SUM(G82:G88) -> 441800 | H89: =SUM(H82:H88) -> 424204 | I89: =SUM(I82:I88) -> 434701 | J89: =SUM(J82:J88) -> 387597.84 | K89: =SUM(K82:K88) -> 347511.02 | L89: =SUM(L82:L88) -> 308244.28 | M89: =SUM(M82:M88) -> 270159.35 | N89: =SUM(N82:N88) -> 231526.25
B90: Total liabilities | G90: =G89+G81 -> 535451 | H90: =H89+H81 -> 527504 | I90: =I89+I81 -> 530299 | J90: =J81+J89 -> 483291.38 | K90: =K81+K89 -> 446051.65 | L90: =L81+L89 -> 409940.81 | M90: =M81+M89 -> 375983.35 | N90: =N81+N89 -> 342452.16
B92: Shareholders' deficit
B93: Common Stock | G93: 650 | H93: 529 | I93: 513 | J93: =I93 -> 513 | K93: =J93 -> 513 | L93: =K93 -> 513 | M93: =L93 -> 513 | N93: =M93 -> 513
B94: Paid-in capital | G94: 142136 | H94: 6688 | I94: 0 | J94: =Schedule!J121 -> 7699.8804 | K94: =Schedule!K121 -> 17377.667 | L94: =Schedule!L121 -> 27193.668 | M94: =Schedule!M121 -> 36741.839 | N94: =Schedule!N121 -> 46645.095
B95: Deficit | G95: -41729 | H95: -21784 | I95: -2499 | J95: =Schedule!J117 -> 26036.673 | K95: =Schedule!K117 -> 55496.073 | L95: =Schedule!L117 -> 84282.419 | M95: =Schedule!M117 -> 114856.97 | N95: =Schedule!N117 -> 145152.89
B96: Accumulated other comprehensive loss, net | G96: -42697 | H96: -41659 | I96: -32039 | J96: =I96 -> -32039 | K96: =J96 -> -32039 | L96: =K96 -> -32039 | M96: =L96 -> -32039 | N96: =M96 -> -32039
B97: Treasury stock | G97: -95476 | H97: -6460 | I97: 0 | J97: =I97 -> 0 | K97: =J97 -> 0 | L97: =K97 -> 0 | M97: =L97 -> 0 | N97: =M97 -> 0
B98: Total shareholders' deficit | G98: =SUM(G93:G97) -> -37116 | H98: =SUM(H93:H97) -> -62686 | I98: =SUM(I93:I97) -> -34025 | J98: =SUM(J93:J97) -> 2210.5536 | K98: =SUM(K93:K97) -> 41347.74 | L98: =SUM(L93:L97) -> 79950.087 | M98: =SUM(M93:M97) -> 120072.81 | N98: =SUM(N93:N97) -> 160271.99
B99: Total liabilities and shareholders' deficit | G99: =G90+G98 -> 498335 | H99: =H90+H98 -> 464818 | I99: =I90+I98 -> 496274 | J99: =J90+J98 -> 485501.93 | K99: =K90+K98 -> 487399.39 | L99: =L90+L98 -> 489890.9 | M99: =M90+M98 -> 496056.16 | N99: =N90+N98 -> 502724.14
C101: Check | G101: =IF(G99=G73,TRUE,G73-G99) -> TRUE | H101: =IF(H99=H73,TRUE,H73-H99) -> TRUE | I101: =IF(I99=I73,TRUE,I73-I99) -> TRUE | J101: =IF(J99=J73,TRUE,J73-J99) -> TRUE | K101: =IF(K99=K73,TRUE,K73-K99) -> TRUE | L101: =IF(L99=L73,TRUE,L73-L99) -> TRUE | M101: =IF(M99=M73,TRUE,M73-M99) -> TRUE | N101: =IF(N99=N73,TRUE,N73-N99) -> TRUE
A103: # | B103: Cash Flow Statement | G103: 44920 | H103: 45285 | I103: 45651 | J103: 46016 | K103: 46381 | L103: 46746 | M103: 47112 | N103: 47477
B105: Net income | J105: =J45 -> 30035.673 | K105: =K45 -> 30959.4 | L105: =L45 -> 30286.345 | M105: =M45 -> 32074.551 | N105: =N45 -> 31795.921
B106: Add/Less: Non-cash items
B107: Depreciation & Amortization | J107: =J35 -> 13724.577 | K107: =K35 -> 13914.684 | L107: =L35 -> 14602.521 | M107: =M35 -> 15365.381 | N107: =N35 -> 16163.077
B108: Share-based compensation | J108: =Schedule!J120 -> 7699.8804 | K108: =Schedule!K120 -> 9677.7862 | L108: =Schedule!L120 -> 9816.0015 | M108: =Schedule!M120 -> 9548.1705 | N108: =Schedule!N120 -> 9903.2566
B109: Interest expenses | J109: =J41 -> 16021.14 | K109: =K41 -> 12912.75 | L109: =L41 -> 9910.15 | M109: =M41 -> 7234.5 | N109: =N41 -> 4563.2
B110: Change in working capital
B111: Receivables | J111: =I61-J61 -> -127.92282 | K111: =J61-K61 -> -517.03396 | L111: =K61-L61 -> -998.46364 | M111: =L61-M61 -> -1115.0697 | N111: =M61-N61 -> -1328.4448
B112: Inventories | J112: =I62-J62 -> 20.378012 | K112: =J62-K62 -> -61.943575 | L112: =K62-L62 -> -117.23738 | M112: =L62-M62 -> -114.99968 | N112: =M62-N62 -> -151.32143
B113: Prepaid and other current assets | J113: =I64-J64 -> -1293.5908 | K113: =J64-K64 -> -60.362663 | L113: =K64-L64 -> -171.0691 | M113: =L64-M64 -> -801.28353 | N113: =M64-N64 -> -547.53177
B114: Accounts payable | J114: =J79-I79 -> -233.11653 | K114: =K79-J79 -> 708.61038 | L114: =L79-K79 -> 1341.15 | M114: =M79-L79 -> 1315.5515 | N114: =N79-M79 -> 1731.0583
B115: Other current liabilities | J115: =J80-I80 -> 328.65294 | K115: =K80-J80 -> 2138.4784 | L115: =L80-K80 -> 1814.7563 | M115: =M80-L80 -> 2811.9104 | N115: =N80-M80 -> 3370.8521
B116: Other noncurrent liabilities | J116: =J88-I88 -> 2896.8443 | K116: =K88-J88 -> -86.820469 | L116: =L88-K88 -> 733.25558 | M116: =M88-L88 -> 1915.0756 | N116: =N88-M88 -> 1366.8977
B117: Cash flow from operating activities | J117: =SUM(J105:J116) -> 69072.515 | K117: =SUM(K105:K116) -> 69585.549 | L117: =SUM(L105:L116) -> 67217.409 | M117: =SUM(M105:M116) -> 68233.788 | N117: =SUM(N105:N116) -> 66866.965
B119: Purchases for PP&E | J119: =-Schedule!J24 -> -9094.0453 | K119: =-Schedule!K24 -> -10214.033 | L119: =-Schedule!L24 -> -11586.217 | M119: =-Schedule!M24 -> -13088.467 | N119: =-Schedule!N24 -> -14783.899
B120: Disposal of PP&E | J120: =-Schedule!J19 -> 4500 | K120: =-Schedule!K19 -> 3000 | L120: =-Schedule!L19 -> 2800 | M120: =-Schedule!M19 -> 1700 | N120: =-Schedule!N19 -> 1500
...

Sheet Assumptions
B2: =Dashboard!B2 -> Denny's Diner
B3: Assumptions
B4: =Dashboard!B4 -> (In $ thousands, except per share amounts)
B5: Active Scenario | D5: =Dashboard!G13 -> Street
B6: Historicals / Forecast | G6: Historicals | J6: Forecast | O6: CAGR | Q6: Notes
B7: Month / Year (A/E) | G7: =Statements!G7 -> 44920 | H7: =EDATE(G7,12) -> 45285 | I7: =EDATE(H7,12) -> 45651 | J7: =EDATE(I7,12) -> 46016 | K7: =EDATE(J7,12) -> 46381 | L7: =EDATE(K7,12) -> 46746 | M7: =EDATE(L7,12) -> 47112 | N7: =EDATE(M7,12) -> 47477 | O7: 22A - 24A | P7: 25E - 29E
B9: <-Back to dashboard
B11: Go to -> | C11: Revenue forecast | E11: Expense forecast
B13: Senarios
B14: Optimistic
B15: Street
B16: Pessimistic
A18: # | B18: Revenue Forecast ($ thousands) | G18: 44920 | H18: 45285 | I18: 45651 | J18: 46016 | K18: 46381 | L18: 46746 | M18: 47112 | N18: 47477
B20: Company restaurant sales:
B21: Denny's | G21: 193576 | H21: 201175 | I21: 193572 | J21: =I21*(1+J$77) -> 193313.73 | K21: =J21*(1+K$77) -> 196154.68 | L21: =K21*(1+L$77) -> 202869.65 | M21: =L21*(1+M$77) -> 210230.3 | N21: =M21*(1+N$77) -> 218882.28
B22: Others (Keke's) | G22: 6177 | H22: 14357 | I22: 18209 | J22: =I22*(1+J$79) -> 20320.188 | K22: =J22*(1+K$79) -> 22695.275 | L22: =K22*(1+L$79) -> 25334.261 | M22: =L22*(1+M$79) -> 28501.043 | N22: =M22*(1+N$79) -> 32459.522
B23: Total company restaurant sales | G23: =SUM(G21:G22) -> 199753 | H23: =SUM(H21:H22) -> 215532 | I23: =SUM(I21:I22) -> 211781 | J23: =SUM(J21:J22) -> 213633.92 | K23: =SUM(K21:K22) -> 218849.96 | L23: =SUM(L21:L22) -> 228203.92 | M23: =SUM(M21:M22) -> 238731.34 | N23: =SUM(N21:N22) -> 251341.8 | O23: =_xlfn.RRI(2,G23,I23) -> 0.029667114 | P23: =_xlfn.RRI(4,J23,N23) -> 0.041474472
B25: Franchise and license revenue:
B26: Royalties
B27: Denny's | G27: 111718 | H27: 115004 | I27: 113804 | J27: =I27*(1+J$77) -> 113652.16 | K27: =J27*(1+K$77) -> 115322.4 | L27: =K27*(1+L$77) -> 119270.24 | M27: =L27*(1+M$77) -> 123597.67 | N27: =M27*(1+N$77) -> 128684.31
B28: Others (Keke's) | G28: 2173 | H28: 5127 | I28: 4901 | J28: =I28*(1+J$79) -> 5469.2319 | K28: =J28*(1+K$79) -> 6108.4928 | L28: =K28*(1+L$79) -> 6818.7826 | M28: =L28*(1+M$79) -> 7671.1304 | N28: =M28*(1+N$79) -> 8736.5652
B29: Total | G29: =SUM(G27:G28) -> 113891 | H29: =SUM(H27:H28) -> 120131 | I29: =SUM(I27:I28) -> 118705 | J29: =SUM(J27:J28) -> 119121.39 | K29: =SUM(K27:K28) -> 121430.89 | L29: =SUM(L27:L28) -> 126089.02 | M29: =SUM(M27:M28) -> 131268.8 | N29: =SUM(N27:N28) -> 137420.87 | O29: =_xlfn.RRI(2,G29,I29) -> 0.020915513 | P29: =_xlfn.RRI(4,J29,N29) -> 0.036372158
B30: Advertising revenue
B31: Denny's | G31: 75926 | H31: 77932 | I31: 78192 | J31: =I31*(1+J$77) -> 78087.674 | K31: =J31*(1+K$77) -> 79235.256 | L31: =K31*(1+L$77) -> 81947.72 | M31: =L31*(1+M$77) -> 84920.998 | N31: =M31*(1+N$77) -> 88415.904
B32: Others (Keke's) | G32: 0 | H32: 562 | I32: 1781 | J32: =I32*(1+J$79) -> 1987.4928 | K32: =J32*(1+K$79) -> 2219.7971 | L32: =K32*(1+L$79) -> 2477.913 | M32: =L32*(1+M$79) -> 2787.6522 | N32: =M32*(1+N$79) -> 3174.8261
B33: Total | G33: =SUM(G31:G32) -> 75926 | H33: =SUM(H31:H32) -> 78494 | I33: =SUM(I31:I32) -> 79973 | J33: =SUM(J31:J32) -> 80075.167 | K33: =SUM(K31:K32) -> 81455.053 | L33: =SUM(L31:L32) -> 84425.633 | M33: =SUM(M31:M32) -> 87708.65 | N33: =SUM(N31:N32) -> 91590.73 | O33: =_xlfn.RRI(2,G33,I33) -> 0.026304974 | P33: =_xlfn.RRI(4,J33,N33) -> 0.034161621
B34: Initial and other fees
B35: Denny's | G35: 27870 | H35: 13112 | I35: 8351 | J35: =I35*(1+J$77) -> 8339.8579 | K35: =J35*(1+K$77) -> 8462.4209 | L35: =K35*(1+L$77) -> 8752.1154 | M35: =L35*(1+M$77) -> 9069.6651 | N35: =M35*(1+N$77) -> 9442.9253
B36: Others (Keke's) | G36: 392 | H36: 770 | I36: 360 | J36: =I36*(1+J$79) -> 401.73913 | K36: =J36*(1+K$79) -> 448.69565 | L36: =K36*(1+L$79) -> 500.86957 | M36: =L36*(1+M$79) -> 563.47826 | N36: =M36*(1+N$79) -> 641.73913
B37: Total | G37: =SUM(G35:G36) -> 28262 | H37: =SUM(H35:H36) -> 13882 | I37: =SUM(I35:I36) -> 8711 | J37: =SUM(J35:J36) -> 8741.597 | K37: =SUM(K35:K36) -> 8911.1166 | L37: =SUM(L35:L36) -> 9252.985 | M37: =SUM(M35:M36) -> 9633.1434 | N37: =SUM(N35:N36) -> 10084.664 | O37: =_xlfn.RRI(2,G37,I37) -> -0.4448216 | P37: =_xlfn.RRI(4,J37,N37) -> 0.036376763
B38: Occupancy revenue
B39: Denny's | G39: 38597 | H39: 35883 | I39: 33075 | J39: =I39*(1+J$77) -> 33030.871 | K39: =J39*(1+K$77) -> 33516.294 | L39: =K39*(1+L$77) -> 34663.659 | M39: =L39*(1+M$77) -> 35921.348 | N39: =M39*(1+N$77) -> 37399.683
B40: Others (Keke's) | G40: 0 | H40: 0 | I40: 89 | J40: =I40*(1+J$79) -> 99.318841 | K40: =J40*(1+K$79) -> 110.92754 | L40: =K40*(1+L$79) -> 123.82609 | M40: =L40*(1+M$79) -> 139.30435 | N40: =M40*(1+N$79) -> 158.65217
B41: Total | G41: =SUM(G39:G40) -> 38597 | H41: =SUM(H39:H40) -> 35883 | I41: =SUM(I39:I40) -> 33164 | J41: =SUM(J39:J40) -> 33130.189 | K41: =SUM(K39:K40) -> 33627.222 | L41: =SUM(L39:L40) -> 34787.485 | M41: =SUM(M39:M40) -> 36060.652 | N41: =SUM(N39:N40) -> 37558.335 | O41: =_xlfn.RRI(2,G41,I41) -> -0.073049211 | P41: =_xlfn.RRI(4,J41,N41) -> 0.031859588
B42: Total Franchise and license revenue | G42: =G29+G33+G37+G41 -> 256676 | H42: =H29+H33+H37+H41 -> 248390 | I42: =I29+I33+I37+I41 -> 240553 | J42: =J29+J33+J37+J41 -> 241068.35 | K42: =K29+K33+K37+K41 -> 245424.28 | L42: =L29+L33+L37+L41 -> 254555.12 | M42: =M29+M33+M37+M41 -> 264671.25 | N42: =N29+N33+N37+N41 -> 276654.6 | O42: =_xlfn.RRI(2,G42,I42) -> -0.031916635 | P42: =_xlfn.RRI(4,J42,N42) -> 0.035021637
B44: Total revenue from Denny's | G44: =G21+G27+G31+G35+G39 -> 447687 | H44: =H21+H27+H31+H35+H39 -> 443106 | I44: =I21+I27+I31+I35+I39 -> 426994 | J44: =J21+J27+J31+J35+J39 -> 426424.29 | K44: =K21+K27+K31+K35+K39 -> 432691.05 | L44: =L21+L27+L31+L35+L39 -> 447503.38 | M44: =M21+M27+M31+M35+M39 -> 463739.98 | N44: =N21+N27+N31+N35+N39 -> 482825.1
B45: Total revenue from Keke's | G45: =G22+G28+G32+G36+G40 -> 8742 | H45: =H22+H28+H32+H36+H40 -> 20816 | I45: =I22+I28+I32+I36+I40 -> 25340 | J45: =J22+J28+J32+J36+J40 -> 28277.971 | K45: =K22+K28+K32+K36+K40 -> 31583.188 | L45: =L22+L28+L32+L36+L40 -> 35255.652 | M45: =M22+M28+M32+M36+M40 -> 39662.609 | N45: =N22+N28+N32+N36+N40 -> 45171.304
B46: Total Revenue | G46: =G23+G42 -> 456429 | H46: =H23+H42 -> 463922 | I46: =I23+I42 -> 452334 | J46: =J23+J42 -> 454702.27 | K46: =K23+K42 -> 464274.24 | L46: =L23+L42 -> 482759.04 | M46: =M23+M42 -> 503402.59 | N46: =N23+N42 -> 527996.41
B48: Analysis
B49: Company-owned restaurants
B50: Denny's | G50: 66 | H50: 65 | I50: 61 | J50: =ROUNDUP(I50*(1+J51),0) -> 59 | K50: =ROUNDUP(J50*(1+K51),0) -> 59 | L50: =ROUNDUP(K50*(1+L51),0) -> 61 | M50: =ROUNDUP(L50*(1+M51),0) -> 63 | N50: =ROUNDUP(M50*(1+N51),0) -> 67 | O50: =_xlfn.RRI(2,G50,I50) -> -0.038624722 | P50: =_xlfn.RRI(4,J50,N50) -> 0.032299454
J51: =OFFSET(J51,MATCH($D$5,$B52:$B54,0),0) -> -0.038344988 | K51: =OFFSET(K51,MATCH($D$5,$B52:$B54,0),0) -> -0.016258741 | L51: =OFFSET(L51,MATCH($D$5,$B52:$B54,0),0) -> 0.02 | M51: =OFFSET(M51,MATCH($D$5,$B52:$B54,0),0) -> 0.032 | N51: =OFFSET(N51,MATCH($D$5,$B52:$B54,0),0) -> 0.05
B52: Optimistic | J52: =J53+$Q$52 -> -0.025844988 | K52: =K53+$Q$52 -> -0.0037587413 | L52: =L53+$Q$52 -> 0.0325 | M52: =M53+$Q$52 -> 0.0445 | N52: =N53+$Q$52 -> 0.0625 | Q52: 0.0125
B53: Street | H53: =H50/G50-1 -> -0.015151515 | I53: =I50/H50-1 -> -0.061538462 | J53: =AVERAGE(H53:I53) -> -0.038344988 | K53: =J53+($N$53-$J$53)/4 -> -0.016258741 | L53: 0.02 | M53: 0.032 | N53: 0.05
B54: Pessimistic | J54: =J53+$Q$54 -> -0.048344988 | K54: =K53+$Q$54 -> -0.026258741 | L54: =L53+$Q$54 -> 0.01 | M54: =M53+$Q$54 -> 0.022 | N54: =N53+$Q$54 -> 0.04 | Q54: -0.01
B55: Keke's | G55: 8 | H55: 8 | I55: 14 | J55: =ROUNDUP(I55*(1+J56),0) -> 16 | K55: =ROUNDUP(J55*(1+K56),0) -> 18 | L55: =ROUNDUP(K55*(1+L56),0) -> 20 | M55: =ROUNDUP(L55*(1+M56),0) -> 23 | N55: =ROUNDUP(M55*(1+N56),0) -> 27 | O55: =_xlfn.RRI(2,G55,I55) -> 0.32287566 | P55: =_xlfn.RRI(4,J55,N55) -> 0.13975353
J56: =OFFSET(J56,MATCH($D$5,$B57:$B59,0),0) -> 0.08 | K56: =OFFSET(K56,MATCH($D$5,$B57:$B59,0),0) -> 0.1 | L56: =OFFSET(L56,MATCH($D$5,$B57:$B59,0),0) -> 0.11 | M56: =OFFSET(M56,MATCH($D$5,$B57:$B59,0),0) -> 0.125 | N56: =OFFSET(N56,MATCH($D$5,$B57:$B59,0),0) -> 0.15
B57: Optimistic | J57: =J58+$Q$52 -> 0.0925 | K57: =K58+$Q$52 -> 0.1125 | L57: =L58+$Q$52 -> 0.1225 | M57: =M58+$Q$52 -> 0.1375 | N57: =N58+$Q$52 -> 0.1625
B58: Street | H58: =H55/G55-1 -> 0 | I58: =I55/H55-1 -> 0.75 | J58: 0.08 | K58: 0.1 | L58: 0.11 | M58: 0.125 | N58: 0.15
B59: Pessimistic | J59: =J58+$Q$54 -> 0.07 | K59: =K58+$Q$54 -> 0.09 | L59: =L58+$Q$54 -> 0.1 | M59: =M58+$Q$54 -> 0.115 | N59: =N58+$Q$54 -> 0.14
B60: Total | G60: =G50+G55 -> 74 | H60: =H50+H55 -> 73 | I60: =I50+I55 -> 75 | J60: =J50+J55 -> 75 | K60: =K50+K55 -> 77 | L60: =L50+L55 -> 81 | M60: =M50+M55 -> 86 | N60: =N50+N55 -> 94 | O60: =_xlfn.RRI(2,G60,I60) -> 0.0067340828 | P60: =_xlfn.RRI(4,J60,N60) -> 0.058075474
B62: Franchised restaurants
B63: Denny's | G63: 1536 | H63: 1508 | I63: 1438 | J63: =ROUNDUP(I63*(1+J64),0) -> 1438 | K63: =ROUNDUP(J63*(1+K64),0) -> 1460 | L63: =ROUNDUP(K63*(1+L64),0) -> 1510 | M63: =ROUNDUP(L63*(1+M64),0) -> 1565 | N63: =ROUNDUP(M63*(1+N64),0) -> 1628 | O63: =_xlfn.RRI(2,G63,I63) -> -0.03242679 | P63: =_xlfn.RRI(4,J63,N63) -> 0.031511036
J64: =OFFSET(J64,MATCH($D$5,$B65:$B67,0),0) -> 0 | K64: =OFFSET(K64,MATCH($D$5,$B65:$B67,0),0) -> 0.015 | L64: =OFFSET(L64,MATCH($D$5,$B65:$B67,0),0) -> 0.034 | M64: =OFFSET(M64,MATCH($D$5,$B65:$B67,0),0) -> 0.036 | N64: =OFFSET(N64,MATCH($D$5,$B65:$B67,0),0) -> 0.04
B65: Optimistic | J65: =J66+$Q$52 -> 0.0125 | K65: =K66+$Q$52 -> 0.0275 | L65: =L66+$Q$52 -> 0.0465 | M65: =M66+$Q$52 -> 0.0485 | N65: =N66+$Q$52 -> 0.0525
B66: Street | H66: =H63/G63-1 -> -0.018229167 | I66: =I63/H63-1 -> -0.046419098 | J66: 0 | K66: 0.015 | L66: 0.034 | M66: 0.036 | N66: 0.04
B67: Pessimistic | J67: =J66+$Q$54 -> -0.01 | K67: =K66+$Q$54 -> 0.005 | L67: =L66+$Q$54 -> 0.024 | M67: =M66+$Q$54 -> 0.026 | N67: =N66+$Q$54 -> 0.03
B68: Keke's | G68: 46 | H68: 50 | I68: 55 | J68: =ROUNDUP(I68*(1+J69),0) -> 61 | K68: =ROUNDUP(J68*(1+K69),0) -> 68 | L68: =ROUNDUP(K68*(1+L69),0) -> 76 | M68: =ROUNDUP(L68*(1+M69),0) -> 85 | N68: =ROUNDUP(M68*(1+N69),0) -> 96 | O68: =_xlfn.RRI(2,G68,I68) -> 0.093458812 | P68: =_xlfn.RRI(4,J68,N68) -> 0.12004468
J69: =OFFSET(J69,MATCH($D$5,$B70:$B72,0),0) -> 0.1 | K69: =OFFSET(K69,MATCH($D$5,$B70:$B72,0),0) -> 0.105 | L69: =OFFSET(L69,MATCH($D$5,$B70:$B72,0),0) -> 0.11 | M69: =OFFSET(M69,MATCH($D$5,$B70:$B72,0),0) -> 0.115 | N69: =OFFSET(N69,MATCH($D$5,$B70:$B72,0),0) -> 0.12
B70: Optimistic | J70: =J71+$Q$52 -> 0.1125 | K70: =K71+$Q$52 -> 0.1175 | L70: =L71+$Q$52 -> 0.1225 | M70: =M71+$Q$52 -> 0.1275 | N70: =N71+$Q$52 -> 0.1325
B71: Street | H71: =H68/G68-1 -> 0.086956522 | I71: =I68/H68-1 -> 0.1 | J71: 0.1 | K71: =J71+($N$71-$J$71)/4 -> 0.105 | L71: =K71+($N$71-$J$71)/4 -> 0.11 | M71: =L71+($N$71-$J$71)/4 -> 0.115 | N71: 0.12
B72: Pessimistic | J72: =J71+$Q$54 -> 0.09 | K72: =K71+$Q$54 -> 0.095 | L72: =L71+$Q$54 -> 0.1 | M72: =M71+$Q$54 -> 0.105 | N72: =N71+$Q$54 -> 0.11
B73: Total | G73: =G63+G68 -> 1582 | H73: =H63+H68 -> 1558 | I73: =I63+I68 -> 1493 | J73: =J63+J68 -> 1499 | K73: =K63+K68 -> 1528 | L73: =L63+L68 -> 1586 | M73: =M63+M68 -> 1650 | N73: =N63+N68 -> 1724 | O73: =_xlfn.RRI(2,G73,I73) -> -0.028536105 | P73: =_xlfn.RRI(4,J73,N73) -> 0.035580603
B75: Total no. of restaurants
B76: Denny's | G76: =G50+G63 -> 1602 | H76: =H50+H63 -> 1573 | I76: =I50+I63 -> 1499 | J76: =J50+J63 -> 1497 | K76: =K50+K63 -> 1519 | L76: =L50+L63 -> 1571 | M76: =M50+M63 -> 1628 | N76: =N50+N63 -> 1695
B77: Growth (YoY %) | H77: =H76/G76-1 -> -0.018102372 | I77: =I76/H76-1 -> -0.047043865 | J77: =J76/I76-1 -> -0.0013342228 | K77: =K76/J76-1 -> 0.014696059 | L77: =L76/K76-1 -> 0.034233048 | M77: =M76/L76-1 -> 0.036282623 | N77: =N76/M76-1 -> 0.041154791
B78: Keke's | G78: =G55+G68 -> 54 | H78: =H55+H68 -> 58 | I78: =I55+I68 -> 69 | J78: =J55+J68 -> 77 | K78: =K55+K68 -> 86 | L78: =L55+L68 -> 96 | M78: =M55+M68 -> 108 | N78: =N55+N68 -> 123
B79: Growth (YoY %) | H79: =H78/G78-1 -> 0.074074074 | I79: =I78/H78-1 -> 0.18965517 | J79: =J78/I78-1 -> 0.11594203 | K79: =K78/J78-1 -> 0.11688312 | L79: =L78/K78-1 -> 0.11627907 | M79: =M78/L78-1 -> 0.125 | N79: =N78/M78-1 -> 0.13888889
B80: Total | G80: =SUM(G76:G78) -> 1656 | H80: =SUM(H76:H78) -> 1630.9819 | I80: =SUM(I76:I78) -> 1567.953 | J80: =SUM(J76:J78) -> 1573.9987 | K80: =SUM(K76:K78) -> 1605.0147 | L80: =SUM(L76:L78) -> 1667.0342 | M80: =SUM(M76:M78) -> 1736.0363 | N80: =SUM(N76:N78) -> 1818.0412 | O80: =_xlfn.RRI(2,G80,I80) -> -0.026947332 | P80: =_xlfn.RRI(4,J80,N80) -> 0.036692216
B81: Growth (YoY %) | H81: =H80/G80-1 -> -0.01510755 | I81: =I80/H80-1 -> -0.038644783 | J81: =J80/I80-1 -> 0.0038557979 | K81: =K80/J80-1 -> 0.019705246 | L81: =L80/K80-1 -> 0.038641102 | M81: =M80/L80-1 -> 0.041392101 | N81: =N80/M80-1 -> 0.047236842
A83: # | B83: Cost forecast ($ thousands) | G83: 44920 | H83: 45285 | I83: 45651 | J83: 46016 | K83: 46381 | L83: 46746 | M83: 47112 | N83: 47477
B85: Costs of company restaurant sales:
B86: Product costs | G86: =Statements!G27 -> 53617 | H86: =Statements!H27 -> 55789 | I86: =Statements!I27 -> 53931 | J86: =J80*J87 -> 55718.533 | K86: =K80*K87 -> 57048.894 | L86: =L80*L87 -> 60191.558 | M86: =M80*M87 -> 63708.953 | N86: =N80*N87 -> 67525.477 | O86: =_xlfn.RRI(2,G86,I86) -> 0.0029239012 | P86: =_xlfn.RRI(4,J86,N86) -> 0.049221055 | Q86: Products sold in restaurants are affected by commodity pricing and are subject to price volatility. (PPIACO)
B87: Product costs per restaurant | G87: =G86/G$80 -> 32.377415 | H87: =H86/H$80 -> 34.205775 | I87: =I86/I$80 -> 34.395802 | J87: =I87*(1+J91) -> 35.399352 | K87: =J87*(1+K91) -> 35.544157 | L87: =K87*(1+L91) -> 36.106972 | M87: =L87*(1+M91) -> 36.697939 | N87: =M87*(1+N91) -> 37.141886 | Q87: (Producer Price Index by Commodity: All Commodities)
B88: Producer commodity prices | G88: 257.897 | H88: 249.866 | I88: 253.423 | J88: 260.817 | K88: =J88*(1+K89) -> 261.8839 | L88: =K88*(1+L89) -> 266.03063 | M88: =L88*(1+M89) -> 270.38479 | N88: =M88*(1+N89) -> 273.65572
K89: =OFFSET(K89,MATCH($D$5,$B90:$B92,0),0) -> 0.0040906022 | L89: =OFFSET(L89,MATCH($D$5,$B90:$B92,0),0) -> 0.015834249 | M89: =OFFSET(M89,MATCH($D$5,$B90:$B92,0),0) -> 0.016367122 | N89: =OFFSET(N89,MATCH($D$5,$B90:$B92,0),0) -> 0.012097325
B90: Optimistic | K90: =K91+$Q$90 -> -0.00090939784 | L90: =L91+$Q$90 -> 0.010834249 | M90: =M91+$Q$90 -> 0.011367122 | N90: =N91+$Q$90 -> 0.0070973245 | Q90: -0.005
B91: Street | H91: =H88/G88-1 -> -0.031140339 | I91: =I88/H88-1 -> 0.01423563 | J91: =J88/I88-1 -> 0.029176515 | K91: =AVERAGE(H91:J91) -> 0.0040906022 | L91: =AVERAGE(I91:K91) -> 0.015834249 | M91: =AVERAGE(J91:L91) -> 0.016367122 | N91: =AVERAGE(K91:M91) -> 0.012097325
B92: Pessimistic | K92: =K91+$Q$92 -> 0.014090602 | L92: =L91+$Q$92 -> 0.025834249 | M92: =M91+$Q$92 -> 0.026367122 | N92: =N91+$Q$92 -> 0.022097325 | Q92: 0.01
B94: Payroll and benefits | G94: =Statements!G28 -> 76412 | H94: =Statements!H28 -> 80666 | I94: =Statements!I28 -> 80605 | J94: =J95*J96 -> 81242.611 | K94: =K95*K96 -> 84511.78 | L94: =L95*L96 -> 91198.44 | M94: =M95*M96 -> 98937.055 | N94: =N95*N96 -> 108511.31 | O94: =_xlfn.RRI(2,G94,I94) -> 0.027070387 | P94: =_xlfn.RRI(4,J94,N94) -> 0.075035432 | Q94: Total human capital per year is linked to an increase in % of total restaurants per year
B95: Payroll per Employees ($) | G95: =G94/G96 -> 20.651892 | H95: =H94/H96 -> 23.047429 | I95: =I94/I96 -> 21.211842 | J95: =($I95/$I$96)*J96 -> 21.295573 | K95: =($I95/$I$96)*K96 -> 21.71981 | L95: =($I95/$I$96)*L96 -> 22.562702 | M95: =($I95/$I$96)*M96 -> 23.500488 | N95: =($I95/$I$96)*N96 -> 24.611319 | Q95: 8-hour shift, 26 days a month, 12-months an year including benefits
B96: Total human capital | G96: 3700 | H96: 3500 | I96: 3800 | J96: =ROUNDUP(I96*(1+J81),0) -> 3815 | K96: =ROUNDUP(J96*(1+K81),0) -> 3891 | L96: =ROUNDUP(K96*(1+L81),0) -> 4042 | M96: =ROUNDUP(L96*(1+M81),0) -> 4210 | N96: =ROUNDUP(M96*(1+N81),0) -> 4409 | Q96: The average hourly earnings in calculated using average of all the payroll and benefits of employees in an restaurant
B97: Average Yearly Earnings ($) | G97: =ROUND(G98*26*8*12,0) -> 24960 | H97: =ROUND(H98*26*8*12,0) -> 26208 | I97: =ROUND(I98*26*8*12,0) -> 28080 | J97: =ROUND(J98*26*8*12,0) -> 29328 | K97: =ROUND(K98*26*8*12,0) -> 30501 | L97: =ROUND(L98*26*8*12,0) -> 32026 | M97: =ROUND(M98*26*8*12,0) -> 33435 | N97: =ROUND(N98*26*8*12,0) -> 34929
B98: Average Hourly Earnings of All Employees ($/Hr) | G98: 10 | H98: 10.5 | I98: 11.25 | J98: 11.75 | K98: =J98*(1+K99) -> 12.22 | L98: =K98*(1+L99) -> 12.831 | M98: =L98*(1+M99) -> 13.395564 | N98: =M98*(1+N99) -> 13.993899
K99: =OFFSET(K99,MATCH($D$5,$B100:$B102,0),0) -> 0.04 | L99: =OFFSET(L99,MATCH($D$5,$B100:$B102,0),0) -> 0.05 | M99: =OFFSET(M99,MATCH($D$5,$B100:$B102,0),0) -> 0.044 | N99: =OFFSET(N99,MATCH($D$5,$B100:$B102,0),0) -> 0.044666667
B100: Optimistic | K100: =K101+$Q$100 -> 0.0325 | L100: =L101+$Q$100 -> 0.0425 | M100: =M101+$Q$100 -> 0.0365 | N100: =N101+$Q$100 -> 0.037166667 | Q100: -0.0075
B101: Street | H101: =H98/G98-1 -> 0.05 | I101: =I98/H98-1 -> 0.071428571 | J101: =J98/I98-1 -> 0.044444444 | K101: 0.04 | L101: 0.05 | M101: 0.044 | N101: {=AVERAGE(K101:M101)} -> 0.044666667
B102: Pessimistic | K102: =K101+$Q$102 -> 0.0525 | L102: =L101+$Q$102 -> 0.0625 | M102: =M101+$Q$102 -> 0.0565 | N102: =N101+$Q$102 -> 0.057166667 | Q102: 0.0125
B104: Occupancy | G104: =Statements!G29 -> 15154 | H104: =Statements!H29 -> 16809 | I104: =Statements!I29 -> 18129 | J104: =J41*J105 -> 15545.869 | K104: =K41*K105 -> 16637.873 | L104: =L41*L105 -> 17517.315 | M104: =M41*M105 -> 17640.413 | N104: =N41*N105 -> 18622.843 | O104: =_xlfn.RRI(2,G104,I104) -> 0.093763139 | P104: =_xlfn.RRI(4,J104,N104) -> 0.046183203 | Q104: Occupancy costs linked to occupancy revenue
B105: Occupancy cost / Occupancy Rev. (%) | G105: =G104/G41 -> 0.39262119 | H105: =H104/H41 -> 0.46843909 | I105: =I104/I41 -> 0.54664697 | J105: =AVERAGE(G105:I105) -> 0.46923575 | K105: =AVERAGE(H105:J105) -> 0.49477394 | L105: =AVERAGE(I105:K105) -> 0.50355222 | M105: =AVERAGE(J105:L105) -> 0.4891873 | N105: =AVERAGE(K105:M105) -> 0.49583782
B107: Other operating expenses | G107: =Statements!G30 -> 34275 | H107: =Statements!H30 -> 34335 | I107: =Statements!I30 -> 37079 | J107: =J108*J46 -> 35023.704 | K107: =K108*K46 -> 36059.944 | L107: =L108*L46 -> 38084.487 | M107: =M108*M46 -> 39195.646 | N107: =N108*N46 -> 41257.666 | O107: =_xlfn.RRI(2,G107,I107) -> 0.040100427 | P107: =_xlfn.RRI(4,J107,N107) -> 0.041803101 | Q107: Other operating costs linked to total revenue
B108: Other operating expenses / Revenue (%) | G108: =G107/G46 -> 0.075093826 | H108: =H107/H46 -> 0.074010286 | I108: =I107/I46 -> 0.081972613 | J108: {=AVERAGE(G108:I108)} -> 0.077025575 | K108: {=AVERAGE(H108:J108)} -> 0.077669492 | L108: {=AVERAGE(I108:K108)} -> 0.078889227 | M108: {=AVERAGE(J108:L108)} -> 0.077861431 | N108: {=AVERAGE(K108:M108)} -> 0.07814005
B110: Costs of franchise and license revenue
B111: Advertising costs | G111: 75926 | H111: 78494 | I111: 79973 | J111: =J112*J$73 -> 75919.474 | K111: =K112*K$73 -> 78739.526 | L111: =L112*L$73 -> 82336.215 | M111: =M112*M$73 -> 84750.73 | N111: =N112*N$73 -> 88963.898 | Q111: Costs of franchise & license costs are linked to the % YoY growth in no. of franchised stores
B112: Advertising costs per Franchised store | G112: =G111/G73 -> 47.993679 | H112: =H111/H73 -> 50.381258 | I112: =I111/I73 -> 53.565305 | J112: =AVERAGE(G112:I112) -> 50.646747 | K112: =AVERAGE(H112:J112) -> 51.531103 | L112: =AVERAGE(I112:K112) -> 51.914385 | M112: =AVERAGE(J112:L112) -> 51.364079 | N112: =AVERAGE(K112:M112) -> 51.603189
B114: Occupancy costs | G114: 24090 | H114: 22160 | I114: 20539 | J114: =J115*J$73 -> 21589.492 | K114: =K115*K$73 -> 21586.985 | L114: =L115*L$73 -> 22355.764 | M114: =M115*M$73 -> 23444.242 | N114: =N115*N$73 -> 24384.216
B115: Occupancy costs per Franchised store | G115: =G114/G73 -> 15.22756 | H115: =H114/H73 -> 14.223363 | I115: =I114/I73 -> 13.756865 | J115: {=AVERAGE(G115:I115)} -> 14.402596 | K115: {=AVERAGE(H115:J115)} -> 14.127608 | L115: {=AVERAGE(I115:K115)} -> 14.09569 | M115: {=AVERAGE(J115:L115)} -> 14.208632 | N115: {=AVERAGE(K115:M115)} -> 14.143977
B117: Other direct costs | G117: 35311 | H117: 21798 | I117: 19714 | J117: =J118*J$73 -> 24741.385 | K117: =K118*K$73 -> 22258.152 | L117: =L118*L$73 -> 23407.457 | M117: =M118*M$73 -> 25207.003 | N117: =N118*N$73 -> 25631.642
B118: Other direct costs per Franchised store | G118: =G117/G73 -> 22.32048 | H118: =H117/H73 -> 13.991014 | I118: =I117/I73 -> 13.204287 | J118: =AVERAGE(G118:I118) -> 16.50526 | K118: =AVERAGE(H118:J118) -> 14.566854 | L118: =AVERAGE(I118:K118) -> 14.7588 | M118: =AVERAGE(J118:L118) -> 15.276971 | N118: =AVERAGE(K118:M118) -> 14.867542
B119: Total costs of franchise and license rev. | G119: =G111+G114+G117 -> 135327 | H119: =H111+H114+H117 -> 122452 | I119: =I111+I114+I117 -> 120226 | J119: =J111+J114+J117 -> 122250.35 | K119: =K111+K114+K117 -> 122584.66 | L119: =L111+L114+L117 -> 128099.44 | M119: =M111+M114+M117 -> 133401.97 | N119: =N111+N114+N117 -> 138979.76 | O119: =_xlfn.RRI(2,G119,I119) -> -0.057444413 | P119: =_xlfn.RRI(4,J119,N119) -> 0.032583918
...

Sheet Schedule
B2: =Dashboard!B2 -> Denny's Diner
B3: Schedule
B4: =Dashboard!B4 -> (In $ thousands, except per share amounts)
B5: Active Scenario | D5: =Dashboard!G13 -> Street
B6: Historicals / Forecast | G6: Historicals | J6: Forecast
B7: Month / Year (A/E) | G7: =Statements!G7 -> 44920 | H7: =EDATE(G7,12) -> 45285 | I7: =EDATE(H7,12) -> 45651 | J7: =EDATE(I7,12) -> 46016 | K7: =EDATE(J7,12) -> 46381 | L7: =EDATE(K7,12) -> 46746 | M7: =EDATE(L7,12) -> 47112 | N7: =EDATE(M7,12) -> 47477
B9: <-Back to dashboard
B11: Go to -> | C11: PP&E and intangibles | E11: Working capital | G11: Equity schedule
A13: # | B13: PP&E and Intangible schedule | G13: 44920 | H13: 45285 | I13: 45651 | J13: 46016 | K13: 46381 | L13: 46746 | M13: 47112 | N13: 47477
B15: Property, plant and equipment
B17: Opening balance of Gross PP&E | H17: =G20 -> 243012 | I17: =H20 -> 253373 | J17: =I20 -> 271005 | K17: =J20 -> 275599.05 | L17: =K20 -> 282813.08 | M17: =L20 -> 291599.3 | N17: =M20 -> 302987.76
B18: Additons to PP&E | J18: =J24 -> 9094.0453 | K18: =K24 -> 10214.033 | L18: =L24 -> 11586.217 | M18: =M24 -> 13088.467 | N18: =N24 -> 14783.899
B19: Disposal of PP&E | J19: -4500 | K19: -3000 | L19: -2800 | M19: -1700 | N19: -1500
B20: Closing balance of Gross PP&E | G20: 243012 | H20: 253373 | I20: 271005 | J20: =SUM(J17:J19) -> 275599.05 | K20: =SUM(K17:K19) -> 282813.08 | L20: =SUM(L17:L19) -> 291599.3 | M20: =SUM(M17:M19) -> 302987.76 | N20: =SUM(N17:N19) -> 316271.66
B21: Less: Accumulated depreciation | I21: 159588 | J21: =I21+J27 -> 171494.71 | K21: =J21+K27 -> 183472.9 | L21: =K21+L27 -> 195827.56 | M21: =L21+M27 -> 208747.5 | N21: =M21+N27 -> 222174.72
B22: Closing balance of Net, PP&E | J22: =J20-J21 -> 104104.34 | K22: =K20-K21 -> 99340.177 | L22: =L20-L21 -> 95771.74 | M22: =M20-M21 -> 94240.268 | N22: =N20-N21 -> 94096.945
B24: CapEx related to PP&E | G24: =4596+91+3846 -> 8533 | H24: =349+4378+3782 -> 8509 | I24: =7471+14970+3420 -> 25861 | J24: =J25*Statements!J25 -> 9094.0453 | K24: =K25*Statements!K25 -> 10214.033 | L24: =L25*Statements!L25 -> 11586.217 | M24: =M25*Statements!M25 -> 13088.467 | N24: =N25*Statements!N25 -> 14783.899
B25: CapEx as a % of Revenue | G25: =G24/Statements!G25 -> 0.018695131 | H25: =H24/Statements!H25 -> 0.018341445 | I25: =I24/Statements!I25 -> 0.057172355 | J25: 0.02 | K25: 0.022 | L25: 0.024 | M25: 0.026 | N25: 0.028
B27: Depreciation of PP&E | G27: 11118 | H27: 10720 | I27: 11260 | J27: =J28*J20 -> 11906.709 | K27: =K28*K20 -> 11978.192 | L27: =L28*L20 -> 12354.654 | M27: =M28*M20 -> 12919.939 | N27: =N28*N20 -> 13427.222
B28: Depreciation as a % of Gross closing PP&E | G28: =G27/G20 -> 0.045750827 | H28: =H27/H20 -> 0.042309165 | I28: =I27/I20 -> 0.041549049 | J28: =AVERAGE(G28:I28) -> 0.043203014 | K28: =AVERAGE(H28:J28) -> 0.042353742 | L28: =AVERAGE(I28:K28) -> 0.042368602 | M28: =AVERAGE(J28:L28) -> 0.042641786 | N28: =AVERAGE(K28:M28) -> 0.04245471
B30: Intangible Assets
B32: Intangible assets with indefinte life | G32: =79687+120 -> 79807 | H32: =79687+120 -> 79807 | I32: =79687+120 -> 79807 | J32: =I32 -> 79807 | K32: =J32 -> 79807 | L32: =K32 -> 79807 | M32: =L32 -> 79807 | N32: =M32 -> 79807
B33: Intangible assets with definte life | G33: =10489+10700 -> 21189 | H33: =9470+10700 -> 20170 | I33: =9135+10603 -> 19738 | J33: =J42+I33 -> 21453.828 | K33: =K42+J33 -> 22895.312 | L33: =L42+K33 -> 24606.953 | M33: =M42+L33 -> 26356.088 | N33: =N42+M33 -> 28138.071
B36: Opening balance of Intangible assets | H36: =G38 -> 100996 | I36: =H38 -> 99977 | J36: =I38 -> 99545 | K36: =J38 -> 101260.83 | L36: =K38 -> 102702.31 | M36: =L38 -> 104413.95 | N36: =M38 -> 106163.09
B37: Additions to intangibles | H37: =H38-H36 -> -1019 | I37: =I38-I36 -> -432 | J37: =J42 -> 1715.8284 | K37: =K42 -> 1441.4837 | L37: =L42 -> 1711.6409 | M37: =M42 -> 1749.1345 | N37: =N42 -> 1781.9832
B38: Closing balance of Intangible assets | G38: 100996 | H38: 99977 | I38: 99545 | J38: =SUM(J36:J37) -> 101260.83 | K38: =SUM(K36:K37) -> 102702.31 | L38: =SUM(L36:L37) -> 104413.95 | M38: =SUM(M36:M37) -> 106163.09 | N38: =SUM(N36:N37) -> 107945.07
B39: Less: Accumulated amortization | I39: 7806 | J39: =I39+J45 -> 9591.1657 | K39: =J39+K45 -> 11496.628 | L39: =K39+L45 -> 13705.419 | M39: =L39+M45 -> 16114.036 | N39: =M39+N45 -> 18811.05
B40: Closing balance of Net, Intangibles | J40: =J38-J39 -> 91669.663 | K40: =K38-K39 -> 91205.684 | L40: =L38-L39 -> 90708.534 | M40: =M38-M39 -> 90049.051 | N40: =N38-N39 -> 89134.02
B42: CapEx related to intangibles | G42: 2638 | H42: 827 | I42: 1700 | J42: =J43*Statements!J25 -> 1715.8284 | K42: =K43*Statements!K25 -> 1441.4837 | L42: =L43*Statements!L25 -> 1711.6409 | M42: =M43*Statements!M25 -> 1749.1345 | N42: =N43*Statements!N25 -> 1781.9832
B43: CapEx as a % of Revenue | G43: =G42/Statements!G25 -> 0.0057796503 | H43: =H42/Statements!H25 -> 0.0017826273 | I43: =I42/Statements!I25 -> 0.0037582848 | J43: {=AVERAGE(G43:I43)} -> 0.0037735208 | K43: {=AVERAGE(H43:J43)} -> 0.0031048109 | L43: {=AVERAGE(I43:K43)} -> 0.0035455388 | M43: {=AVERAGE(J43:L43)} -> 0.0034746235 | N43: {=AVERAGE(K43:M43)} -> 0.0033749911
B45: Total Amortization of Intangibles | G45: 2000 | H45: 2200 | I45: 2200 | J45: =SUM(J46:J52) -> 1785.1657 | K45: =SUM(K46:K52) -> 1905.4624 | L45: =SUM(L46:L52) -> 2208.7906 | M45: =SUM(M46:M52) -> 2408.6175 | N45: =SUM(N46:N52) -> 2697.0142
B46: Amortization of Intangibles (existing) | J46: 1442 | K46: 1274 | L46: 1235 | M46: 1085 | N46: 1017
B48: Amortization of Intangibles (new) | J48: =$J$42/5 -> 343.16569 | K48: =$J$42/5 -> 343.16569 | L48: =$J$42/5 -> 343.16569 | M48: =$J$42/5 -> 343.16569 | N48: =$J$42/5 -> 343.16569
K49: =$K$42/5 -> 288.29675 | L49: =$K$42/5 -> 288.29675 | M49: =$K$42/5 -> 288.29675 | N49: =$K$42/5 -> 288.29675
L50: =$L$42/5 -> 342.32818 | M50: =$L$42/5 -> 342.32818 | N50: =$L$42/5 -> 342.32818
M51: =$M$42/5 -> 349.8269 | N51: =$M$42/5 -> 349.8269
N52: =$N$42/5 -> 356.39664
B53: Other non-current assets
B55: Opening balance of NCA | J55: =Statements!I72 -> 54764 | K55: =J58 -> 49405.293 | L55: =K58 -> 50010.28 | M55: =L58 -> 54300.914 | N55: =M58 -> 55181.589
B56: Additons to NCA | J56: =J58-J57-J55 -> -5326.0052 | K56: =K58-K57-K55 -> 636.01643 | L56: =L58-L57-L55 -> 4329.7098 | M56: =M58-M57-M55 -> 917.49965 | N56: =N58-N57-N55 -> 2904.2433
B57: Less: Amortization of NCA | J57: =-J60 -> -32.701667 | K57: =-K60 -> -31.029698 | L57: =-L60 -> -39.076037 | M57: =-M60 -> -36.824381 | N57: =-N60 -> -38.841516
B58: Closing balance of NCA | J58: =Statements!J72 -> 49405.293 | K58: =Statements!K72 -> 50010.28 | L58: =Statements!L72 -> 54300.914 | M58: =Statements!M72 -> 55181.589 | N58: =Statements!N72 -> 58046.991
B60: Amortization of NCA | G60: 40 | H60: 14 | I60: 48 | J60: =J61*J58 -> 32.701667 | K60: =K61*K58 -> 31.029698 | L60: =L61*L58 -> 39.076037 | M60: =M61*M58 -> 36.824381 | N60: =N61*N58 -> 38.841516
B61: Amortization of NCA as a % of NCA | G61: =G60/G83 -> 0.00078622533 | H61: =H60/H83 -> 0.00032300487 | I61: =I60/I83 -> 0.0008764882 | J61: =AVERAGE(G61:I61) -> 0.00066190613 | K61: =AVERAGE(H61:J61) -> 0.0006204664 | L61: =AVERAGE(I61:K61) -> 0.00071962025 | M61: =AVERAGE(J61:L61) -> 0.00066733093 | N61: =AVERAGE(K61:M61) -> 0.00066913919
A63: # | B63: Working capital schedule
B65: Current assets
B66: Receivables, net | G66: =Statements!G61 -> 25576 | H66: =Statements!H61 -> 21391 | I66: =Statements!I61 -> 24433 | J66: =J73*Statements!J25/days -> 24560.923 | K66: =K73*Statements!K25/days -> 25077.957 | L66: =L73*Statements!L25/days -> 26076.42 | M66: =M73*Statements!M25/days -> 27191.49 | N66: =N73*Statements!N25/days -> 28519.935
B67: Inventories | G67: =Statements!G62 -> 5538 | H67: =Statements!H62 -> 2175 | I67: =Statements!I62 -> 1747 | J67: =J74*Statements!J$31/days -> 1726.622 | K67: =K74*Statements!K$31/days -> 1788.5656 | L67: =L74*Statements!L$31/days -> 1905.8029 | M67: =M74*Statements!M$31/days -> 2020.8026 | N67: =N74*Statements!N$31/days -> 2172.1241
B69: Current liabilities
B70: Accounts payable | G70: =Statements!G79 -> 19896 | H70: =Statements!H79 -> 24070 | I70: =Statements!I79 -> 19985 | J70: =J75*Statements!J$31/days -> 19751.883 | K70: =K75*Statements!K$31/days -> 20460.494 | L70: =L75*Statements!L$31/days -> 21801.644 | M70: =M75*Statements!M$31/days -> 23117.195 | N70: =N75*Statements!N$31/days -> 24848.254
B72: Turnover ratio
B73: Receivables, net | G73: =G66*days/Statements!G$25 -> 20.452776 | H73: =H66*days/Statements!H$25 -> 16.829801 | I73: =I66*days/Statements!I$25 -> 19.715619 | J73: =I73 -> 19.715619 | K73: =J73 -> 19.715619 | L73: =K73 -> 19.715619 | M73: =L73 -> 19.715619 | N73: =M73 -> 19.715619
B74: Inventories | G74: =G67*days/Statements!G$31 -> 11.26375 | H74: =H67*days/Statements!H$31 -> 4.2317656 | I74: =I67*days/Statements!I$31 -> 3.3606069 | J74: =I74 -> 3.3606069 | K74: =J74 -> 3.3606069 | L74: =K74 -> 3.3606069 | M74: =L74 -> 3.3606069 | N74: =M74 -> 3.3606069
B75: Accounts payable | G75: =G70*days/Statements!G$31 -> 40.466516 | H75: =H70*days/Statements!H$31 -> 46.83154 | I75: =I70*days/Statements!I$31 -> 38.444035 | J75: =I75 -> 38.444035 | K75: =J75 -> 38.444035 | L75: =K75 -> 38.444035 | M75: =L75 -> 38.444035 | N75: =M75 -> 38.444035
B77: Prepaid and other current assets | G77: =Statements!G64 -> 12529 | H77: =Statements!H64 -> 12855 | I77: =Statements!I64 -> 10628 | J77: =J78*Statements!J$25 -> 11921.591 | K77: =K78*Statements!K$25 -> 11981.953 | L77: =L78*Statements!L$25 -> 12153.023 | M77: =M78*Statements!M$25 -> 12954.306 | N77: =N78*Statements!N$25 -> 13501.838
B78: Prepaid and other current as a % of revenue | G78: =G77/Statements!G$25 -> 0.027450052 | H78: =H77/Statements!H$25 -> 0.027709399 | I78: =I77/Statements!I$25 -> 0.023495912 | J78: {=AVERAGE(G78:I78)} -> 0.026218455 | K78: {=AVERAGE(H78:J78)} -> 0.025807922 | L78: {=AVERAGE(I78:K78)} -> 0.025174096 | M78: {=AVERAGE(J78:L78)} -> 0.025733491 | N78: {=AVERAGE(K78:M78)} -> 0.025571837
B79: Other current liabilities | G79: =Statements!G80 -> 56762 | H79: =Statements!H80 -> 63068 | I79: =Statements!I80 -> 58842 | J79: =J80*Statements!J$25 -> 59170.653 | K79: =K80*Statements!K$25 -> 61309.131 | L79: =L80*Statements!L$25 -> 63123.888 | M79: =M80*Statements!M$25 -> 65935.798 | N79: =N80*Statements!N$25 -> 69306.65
B80: Other current liabilities as a % of revenue | G80: =G79/Statements!G$25 -> 0.12436107 | H80: =H79/Statements!H$25 -> 0.13594527 | I80: =I79/Statements!I$25 -> 0.13008529 | J80: {=AVERAGE(G80:I80)} -> 0.13013054 | K80: {=AVERAGE(H80:J80)} -> 0.1320537 | L80: {=AVERAGE(I80:K80)} -> 0.13075651 | M80: {=AVERAGE(J80:L80)} -> 0.13098025 | N80: {=AVERAGE(K80:M80)} -> 0.13126349
B81: Other noncurrent liabilities | G81: =Statements!G88 -> 32598 | H81: =Statements!H88 -> 31592 | I81: =Statements!I88 -> 27446 | J81: =J82*Statements!J$25 -> 30342.844 | K81: =K82*Statements!K$25 -> 30256.024 | L81: =L82*Statements!L$25 -> 30989.279 | M81: =M82*Statements!M$25 -> 32904.355 | N81: =N82*Statements!N$25 -> 34271.253
B82: Other noncurrent liabilities as a % of revenue | G82: =G81/Statements!G$25 -> 0.071419651 | H82: =H81/Statements!H$25 -> 0.068097654 | I82: =I81/Statements!I$25 -> 0.060676403 | J82: {=AVERAGE(G82:I82)} -> 0.066731236 | K82: {=AVERAGE(H82:J82)} -> 0.065168431 | L82: {=AVERAGE(I82:K82)} -> 0.064192023 | M82: {=AVERAGE(J82:L82)} -> 0.065363897 | N82: {=AVERAGE(K82:M82)} -> 0.064908117
B83: Other noncurrent assets | G83: =Statements!G72 -> 50876 | H83: =Statements!H72 -> 43343 | I83: =Statements!I72 -> 54764 | J83: =J84*Statements!J25 -> 49405.293 | K83: =K84*Statements!K25 -> 50010.28 | L83: =L84*Statements!L25 -> 54300.914 | M83: =M84*Statements!M25 -> 55181.589 | N83: =N84*Statements!N25 -> 58046.991
B84: Other noncurrent assets as a % of revenue | G84: =G83/Statements!G25 -> 0.11146531 | H84: =H83/Statements!H25 -> 0.093427343 | I84: =I83/Statements!I25 -> 0.12106983 | J84: =AVERAGE(G84:I84) -> 0.10865416 | K84: =AVERAGE(H84:J84) -> 0.10771711 | L84: =AVERAGE(I84:K84) -> 0.11248037 | M84: =AVERAGE(J84:L84) -> 0.10961721 | N84: =AVERAGE(K84:M84) -> 0.10993823
A86: # | B86: Debt Schedule
B88: Opening balance of debt | J88: =Statements!I83 -> 261300 | K88: =Statements!J83 -> 211300 | L88: =Statements!K83 -> 171300 | M88: =Statements!L83 -> 131300 | N88: =Statements!M83 -> 91300
B89: Issuance of new debt | J89: 0 | K89: 0 | L89: 0 | M89: 0 | N89: 0
B90: Less: Repayment of debt | J90: 50000 | K90: 40000 | L90: 40000 | M90: 40000 | N90: 40000
B91: Closing balance of debt | J91: =J88+J89-J90 -> 211300 | K91: =K88+K89-K90 -> 171300 | L91: =L88+L89-L90 -> 131300 | M91: =M88+M89-M90 -> 91300 | N91: =N88+N89-N90 -> 51300
B93: SOFR Curve | D93: SOFR + 2.25% | J93: 0.0453 | K93: 0.045 | L93: 0.043 | M93: 0.0425 | N93: 0.0415
B94: Interest rate | J94: =J93+2.25% -> 0.0678 | K94: =K93+2.25% -> 0.0675 | L94: =L93+2.25% -> 0.0655 | M94: =M93+2.25% -> 0.065 | N94: =N93+2.25% -> 0.064
B95: Interst Expenses | J95: =AVERAGE(J88,J91)*J94 -> 16021.14 | K95: =AVERAGE(K88,K91)*K94 -> 12912.75 | L95: =AVERAGE(L88,L91)*L94 -> 9910.15 | M95: =AVERAGE(M88,M91)*M94 -> 7234.5 | N95: =AVERAGE(N88,N91)*N94 -> 4563.2
B97: Cash flow before debt repayment | J97: =Statements!J117+Statements!J123 -> 68088.647 | K97: =Statements!K117+Statements!K123 -> 60294.015 | L97: =Statements!L117+Statements!L123 -> 52389.842 | M97: =Statements!M117+Statements!M123 -> 54178.686 | N97: =Statements!N117+Statements!N123 -> 48896.839
B98: Less: Minimum cash balance | J98: -2000 | K98: -1999 | L98: -1998 | M98: -1997 | N98: -1996
B99: Cash flow available for debt | J99: =SUM(J97:J98) -> 66088.647 | K99: =SUM(K97:K98) -> 58295.015 | L99: =SUM(L97:L98) -> 50391.842 | M99: =SUM(M97:M98) -> 52181.686 | N99: =SUM(N97:N98) -> 46900.839
B100: Less: Repayment of Long-term Debt | J100: =-J90 -> -50000 | K100: =-K90 -> -40000 | L100: =-L90 -> -40000 | M100: =-M90 -> -40000 | N100: =-N90 -> -40000
B101: Less: Payment of interest expenses | J101: =-J95 -> -16021.14 | K101: =-K95 -> -12912.75 | L101: =-L95 -> -9910.15 | M101: =-M95 -> -7234.5 | N101: =-N95 -> -4563.2
B102: Net cash after debt repayment | J102: =SUM(J99:J101) -> 67.506846 | K102: =SUM(K99:K101) -> 5382.2654 | L102: =SUM(L99:L101) -> 481.69186 | M102: =SUM(M99:M101) -> 4947.1862 | N102: =SUM(N99:N101) -> 2337.6389
B104: Beginning revolver balance | J104: =Statements!I82 -> 0 | K104: =J107 -> 0 | L104: =K107 -> 0 | M104: =L107 -> 0 | N104: =M107 -> 0
B105: Draw on revolver | J105: =IF(J102<0,-J102,0) -> 0 | K105: =IF(K102<0,-K102,0) -> 0 | L105: =IF(L102<0,-L102,0) -> 0 | M105: =IF(M102<0,-M102,0) -> 0 | N105: =IF(N102<0,-N102,0) -> 0
B106: Less: Repayment of revolver debt | J106: =IF(J102>0,MIN(J102,J104),0) -> 0 | K106: =IF(K102>0,-MIN(K102,K104),0) -> 0 | L106: =IF(L102>0,-MIN(L102,L104),0) -> 0 | M106: =IF(M102>0,-MIN(M102,M104),0) -> 0 | N106: =IF(N102>0,-MIN(N102,N104),0) -> 0
B107: Closing revolver balance | J107: =SUM(J104:J106) -> 0 | K107: =SUM(K104:K106) -> 0 | L107: =SUM(L104:L106) -> 0 | M107: =SUM(M104:M106) -> 0 | N107: =SUM(N104:N106) -> 0
B109: Interest rate | D109: SOFR + 1.25% | J109: =J93+1.25% -> 0.0578 | K109: =K93+1.25% -> 0.0575 | L109: =L93+1.25% -> 0.0555 | M109: =M93+1.25% -> 0.055 | N109: =N93+1.25% -> 0.054
B110: Interest expenses on revolver | J110: =AVERAGE(J104,J107)*J109 -> 0 | K110: =AVERAGE(K104,K107)*K109 -> 0 | L110: =AVERAGE(L104,L107)*L109 -> 0 | M110: =AVERAGE(M104,M107)*M109 -> 0 | N110: =AVERAGE(N104,N107)*N109 -> 0
A112: # | B112: Equity schedule
B114: Opening balance of deficit | J114: =Statements!I95 -> -2499 | K114: =J117 -> 26036.673 | L114: =K117 -> 55496.073 | M114: =L117 -> 84282.419 | N114: =M117 -> 114856.97
B115: Add: Net Income | J115: =Statements!J45 -> 30035.673 | K115: =Statements!K45 -> 30959.4 | L115: =Statements!L45 -> 30286.345 | M115: =Statements!M45 -> 32074.551 | N115: =Statements!N45 -> 31795.921
B116: Less: Dividends Paid | J116: -1500 | K116: -1500 | L116: -1500 | M116: -1500 | N116: -1500
B117: Closing balance of deficit | J117: =SUM(J114:J116) -> 26036.673 | K117: =SUM(K114:K116) -> 55496.073 | L117: =SUM(L114:L116) -> 84282.419 | M117: =SUM(M114:M116) -> 114856.97 | N117: =SUM(N114:N116) -> 145152.89
B119: Opening balance of Paid in Capital | J119: =Statements!I94 -> 0 | K119: =J121 -> 7699.8804 | L119: =K121 -> 17377.667 | M119: =L121 -> 27193.668 | N119: =M121 -> 36741.839
B120: Add: Share Based compensation | G120: 6548 | H120: 5546 | I120: 8701 | J120: =J123*Statements!J45 -> 7699.8804 | K120: =K123*Statements!K45 -> 9677.7862 | L120: =L123*Statements!L45 -> 9816.0015 | M120: =M123*Statements!M45 -> 9548.1705 | N120: =N123*Statements!N45 -> 9903.2566
B121: Closing balance of Paid in Capital | J121: =SUM(J119:J120) -> 7699.8804 | K121: =SUM(K119:K120) -> 17377.667 | L121: =SUM(L119:L120) -> 27193.668 | M121: =SUM(M119:M120) -> 36741.839 | N121: =SUM(N119:N120) -> 46645.095
B123: Share based compensation as a % of PAT | G123: =G120/Statements!G45 -> 0.087643217 | H123: =H120/Statements!H45 -> 0.27806468 | I123: =I120/Statements!I45 -> 0.40336563 | J123: =AVERAGE(G123:I123) -> 0.25635784 | K123: =AVERAGE(H123:J123) -> 0.31259605 | L123: =AVERAGE(I123:K123) -> 0.32410651 | M123: =AVERAGE(J123:L123) -> 0.2976868 | N123: =AVERAGE(K123:M123) -> 0.31146312
B125: <- Go back to the top

Sheet Valuation->
A1: \

Sheet WACC
B2: =Dashboard!B2 -> Denny's Diner
B3: WACC
B4: (In $ Millions, except per share amounts and shares outstanding)
B5: Active Scenario | C5: =Dashboard!G13 -> Street
B8: <-Back to dashboard
B10: Company name | C10: Equity Value | D10: Debt | E10: Tax Rate | F10: Levered Beta | G10: Un-Levered Beta
B12: Denny's Diner | C12: =Comp_Comps!F22 -> 328.8375 | D12: =Comp_Comps!G22 -> 211.3 | E12: 0.25 | F12: 1.37 | G12: =F12/(1+(1-E12)*(D12/C12)) -> 0.92447326
B13: Dine Brands Global, Inc. | C13: =Comp_Comps!F15 -> 367.164 | D13: =Comp_Comps!G15 -> 1600 | E13: 0.25 | F13: 0.94 | G13: =F13/(1+(1-E13)*(D13/C13)) -> 0.22022849
B14: Cracker Barrel Old Country Store, Inc. | C14: =Comp_Comps!F16 -> 617.5305 | D14: =Comp_Comps!G16 -> 1210 | E14: 0.25 | F14: 1.22 | G14: =F14/(1+(1-E14)*(D14/C14)) -> 0.49401452
B15: Texas Roadhouse, Inc. | C15: =Comp_Comps!F17 -> 11305.035 | D15: =Comp_Comps!G17 -> 976.76 | E15: 0.25 | F15: 0.87 | G15: =F15/(1+(1-E15)*(D15/C15)) -> 0.81705459
B16: Brinker International, Inc. | C16: =Comp_Comps!F18 -> 6275.7375 | D16: =Comp_Comps!G18 -> 1760 | E16: 0.25 | F16: 1.36 | G16: =F16/(1+(1-E16)*(D16/C16)) -> 1.1236569
B17: Darden Restaurants, Inc. | C17: =Comp_Comps!F19 -> 23079.393 | D17: =Comp_Comps!G19 -> 8350 | E17: 0.25 | F17: 0.6 | G17: =F17/(1+(1-E17)*(D17/C17)) -> 0.47194078
B18: Papa John's International, Inc. | C18: =Comp_Comps!F20 -> 1185.0972 | D18: =Comp_Comps!G20 -> 937.1 | E18: 0.25 | F18: 1.24 | G18: =F18/(1+(1-E18)*(D18/C18)) -> 0.77837981
D20: Average | E20: =AVERAGE(E12:E18) -> 0.25 | F20: =AVERAGE(F12:F18) -> 1.0857143 | G20: =AVERAGE(G12:G18) -> 0.68996405
D21: Median | E21: {=MEDIAN(E12:E18)} -> 0.25 | F21: {=MEDIAN(F12:F18)} -> 1.22 | G21: {=MEDIAN(G12:G18)} -> 0.77837981
B23: Cost of Debt | E23: Weightage
B24: Pre-Tax Cost of debt | C24: =((Statements!J41/1000)/(Statements!J83/1000)) -> 0.07582177 | E24: Equity | G24: =C12 -> 328.8375
B25: Tax Rate | C25: =E21 -> 0.25 | E25: Debt | G25: =D12 -> 211.3
B26: Post-Tax Cost of debt | C26: =C24*(1-C25) -> 0.056866327 | E26: Total | G26: =SUM(G24:G25) -> 540.1375
B28: Cost of Equity | E28: Weighted average cost of capital
B29: Risk free rate | C29: 0.0421 | E29: Cost of Debt | G29: =C26*(G25/G26) -> 0.022245919
B30: Equity risk premium | C30: 0.0446 | E30: Cost of Equity | G30: =C33*(G24/G26) -> 0.060157073
B31: Country risk | C31: 0.0023 | E31: WACC | G31: =G29+G30 -> 0.082402992
B32: Levered Beta | C32: =F21 -> 1.22
B33: Cost of Equity | C33: =C29+(C30*C32)+C31 -> 0.098812

Sheet Comp_Comps
B2: =Dashboard!B2 -> Denny's Diner
B3: Company Comparables
B4: (In $ Millions, except per share amounts and shares outstanding)
B5: Active Scenario | D5: =Dashboard!G13 -> Street
B8: <-Back to dashboard
B10: Comparable companies - US-based operating family-style dine-in & QSR's (In $ Millions)
B12: Valuation statistics
B14: Company name | C14: Ticker | D14: Share price | E14: Diluted Shares | F14: Equity Value | G14: Debt | H14: Cash | I14: Enterprise Value | J14: Revenue | K14: EBITDA | L14: Net Income | M14: EV/Revenue | N14: EV/EBITDA | O14: P/E Multiple
B15: Dine Brands Global, Inc. | C15: IHP.F | D15: 25.2 | E15: 14.57 | F15: =D15*E15 -> 367.164 | G15: 1600 | H15: 128.2 | I15: =F15+G15-H15 -> 1838.964 | J15: 879.3 | K15: 186.5 | L15: 16 | M15: =I15/J15 -> 2.0913954 | N15: =I15/K15 -> 9.8603968 | O15: =D15/(L15/E15) -> 22.94775
B16: Cracker Barrel Old Country Store, Inc. | C16: CBRL | D16: 27.63 | E16: 22.35 | F16: =D16*E16 -> 617.5305 | G16: 1210 | H16: 8.57 | I16: =F16+G16-H16 -> 1818.9605 | J16: 3360 | K16: 130.87 | L16: -4.01 | M16: =I16/J16 -> 0.54135729 | N16: =I16/K16 -> 13.898988 | O16: =D16/(L16/E16) -> -153.99763
B17: Texas Roadhouse, Inc. | C17: TXRH | D17: 170.9 | E17: 66.15 | F17: =D17*E17 -> 11305.035 | G17: 976.76 | H17: 134.71 | I17: =F17+G17-H17 -> 12147.085 | J17: 5880 | K17: 681.73 | L17: 405.55 | M17: =I17/J17 -> 2.0658308 | N17: =I17/K17 -> 17.818029 | O17: =D17/(L17/E17) -> 27.875811
B18: Brinker International, Inc. | C18: EAT | D18: 141.25 | E18: 44.43 | F18: =D18*E18 -> 6275.7375 | G18: 1760 | H18: 15 | I18: =F18+G18-H18 -> 8020.7375 | J18: 5690 | K18: 809.9 | L18: 454.1 | M18: =I18/J18 -> 1.4096199 | N18: =I18/K18 -> 9.9033677 | O18: =D18/(L18/E18) -> 13.820166
B19: Darden Restaurants, Inc. | C19: DRI | D19: 198.43 | E19: 116.31 | F19: =D19*E19 -> 23079.393 | G19: 8350 | H19: 224.1 | I19: =F19+G19-H19 -> 31205.293 | J19: 12580 | K19: 1990 | L19: 1120 | M19: =I19/J19 -> 2.480548 | N19: =I19/K19 -> 15.681052 | O19: =D19/(L19/E19) -> 20.606601
B20: Papa John's International, Inc. | C20: PZZA | D20: 36.12 | E20: 32.81 | F20: =D20*E20 -> 1185.0972 | G20: 937.1 | H20: 36.95 | I20: =F20+G20-H20 -> 2085.2472 | J20: 2050 | K20: 201.79 | L20: 29.57 | M20: =I20/J20 -> 1.0171938 | N20: =I20/K20 -> 10.333749 | O20: =D20/(L20/E20) -> 40.077687
B22: Denny's Diner | C22: DENN | D22: 6.25 | E22: =Statements!J53/1000 -> 52.614 | F22: =D22*E22 -> 328.8375 | G22: =Statements!J83/1000 -> 211.3 | H22: =Statements!J59/1000 -> 2.2655068 | I22: =F22+G22-H22 -> 537.87199 | J22: =Statements!J25/1000 -> 454.70227 | K22: =(Statements!J40+Statements!J35)/1000 -> 70.334464 | L22: =Statements!J45/1000 -> 30.035673 | M22: =I22/J22 -> 1.1829103 | N22: =I22/K22 -> 7.6473461 | O22: =D22/(L22/E22) -> 10.948231
L23: Maxminum | M23: =MAX(M15:M20) -> 2.480548 | N23: =MAX(N15:N20) -> 17.818029 | O23: =MAX(O15:O20) -> 40.077687
L24: 75th percentile | M24: =QUARTILE(M15:M20,3) -> 2.0850043 | N24: =QUARTILE(N15:N20,3) -> 15.235536 | O24: =QUARTILE(O15:O20,3) -> 26.643795
L25: Median | M25: =MEDIAN(M15:M20) -> 1.7377254 | N25: =MEDIAN(N15:N20) -> 12.116368 | O25: =MEDIAN(O15:O20) -> 21.777176
L26: 25th percentile | M26: =QUARTILE(M15:M20,1) -> 1.1153003 | N26: =QUARTILE(N15:N20,1) -> 10.010963 | O26: =QUARTILE(O15:O20,1) -> 15.516775
L27: Minimum | M27: =MIN(M15:M20) -> 0.54135729 | N27: =MIN(N15:N20) -> 9.8603968 | O27: =MIN(O15:O20) -> -153.99763

Sheet FCFF
B2: =Dashboard!B2 -> Denny's Diner
B3: FCFF
B4: =Dashboard!B4 -> (In $ thousands, except per share amounts)
B5: Active Scenario | D5: =Dashboard!G13 -> Street
B8: <-Back to dashboard
B10: Valuation parameters
B12: Valuation as on specified date | E12: 46016 | G12: Implied Price per Share | I12: =G40 -> 8.7223597
B13: Date of year ending | E13: 46022 | G13: Current Price | I13: =Comp_Comps!D22 -> 6.25
B14: Marginal Tax Rate (%) | E14: =WACC!E21 -> 0.25 | G14: Discount | (Premium) | I14: =I13/I12-1 -> -0.28345078
B15: WACC (%) | E15: =WACC!G31 -> 0.082402992
B16: Terminal Growth Rate (%) | E16: 0.02
B18: Free Cash Flow to Firm | G18: =Statements!J7 -> 46016 | H18: =EDATE(G18,12) -> 46381 | I18: =EDATE(H18,12) -> 46746 | J18: =EDATE(I18,12) -> 47112 | K18: =EDATE(J18,12) -> 47477
B20: EBIT | G20: =Statements!J40 -> 56609.888 | H20: =Statements!K40 -> 54749.777 | I20: =Statements!L40 -> 50837.643 | J20: =Statements!M40 -> 50578.488 | K20: =Statements!N40 -> 47530.66
B21: Tax rate (%) | G21: =$E$14 -> 0.25 | H21: =$E$14 -> 0.25 | I21: =$E$14 -> 0.25 | J21: =$E$14 -> 0.25 | K21: =$E$14 -> 0.25
B22: Less: Income taxes | G22: =G20*G21 -> 14152.472 | H22: =H20*H21 -> 13687.444 | I22: =I20*I21 -> 12709.411 | J22: =J20*J21 -> 12644.622 | K22: =K20*K21 -> 11882.665
B23: NOPAT | G23: =G20-G22 -> 42457.416 | H23: =H20-H22 -> 41062.333 | I23: =I20-I22 -> 38128.233 | J23: =J20-J22 -> 37933.866 | K23: =K20-K22 -> 35647.995
B25: Add: Depreciation and Amortisation | G25: =Statements!J107 -> 13724.577 | H25: =Statements!K107 -> 13914.684 | I25: =Statements!L107 -> 14602.521 | J25: =Statements!M107 -> 15365.381 | K25: =Statements!N107 -> 16163.077
B26: Add: Share-based compensation | G26: =Statements!J108 -> 7699.8804 | H26: =Statements!K108 -> 9677.7862 | I26: =Statements!L108 -> 9816.0015 | J26: =Statements!M108 -> 9548.1705 | K26: =Statements!N108 -> 9903.2566
B27: Add/Less: Change in Working capital | G27: =SUM(Statements!J111,Statements!J112,Statements!J114) -> -340.66134 | H27: =SUM(Statements!K111,Statements!K112,Statements!K114) -> 129.63285 | I27: =SUM(Statements!L111,Statements!L112,Statements!L114) -> 225.44902 | J27: =SUM(Statements!M111,Statements!M112,Statements!M114) -> 85.482171 | K27: =SUM(Statements!N111,Statements!N112,Statements!N114) -> 251.29206
B28: Less: Capital Expenditure | G28: =(Statements!J119+Statements!J121+Statements!J122) -> -5483.8685 | H28: =(Statements!K119+Statements!K121+Statements!K122) -> -12291.533 | I28: =(Statements!L119+Statements!L121+Statements!L122) -> -17627.568 | J28: =(Statements!M119+Statements!M121+Statements!M122) -> -15755.101 | K28: =(Statements!N119+Statements!N121+Statements!N122) -> -19470.126
B29: FCFF | G29: =SUM(G23:G28) -> 58057.343 | H29: =SUM(H23:H28) -> 52492.903 | I29: =SUM(I23:I28) -> 45144.637 | J29: =SUM(J23:J28) -> 47177.799 | K29: =SUM(K23:K28) -> 42495.496
B31: Dicount Rate | G31: =(E13-E12)/(365/2) -> 0.032876712 | H31: =G31+1 -> 1.0328767 | I31: =H31+1 -> 2.0328767 | J31: =I31+1 -> 3.0328767 | K31: =J31+1 -> 4.0328767
B32: Terminal Value | K32: =K29*(1+terminal_growth)/(wacc-terminal_growth) -> 694604.6
B33: PV of Cash Flows | G33: =G29/(1+wacc)^G31 -> 57906.399 | H33: =H29/(1+wacc)^H31 -> 48370.548 | I33: =I29/(1+wacc)^I31 -> 38432.408 | J33: =J29/(1+wacc)^J31 -> 37105.657 | K33: =(K29+K32)/(1+wacc)^K31 -> 535599.22
B34: Enterprise Value | G34: =SUM(G33:K33) -> 717414.23
B35: Add: Cash | G35: =Statements!I59 -> 1698
B36: Add: Investments & Securities | G36: =Statements!I60 -> 1106
B37: Less: Debt | G37: =-Statements!I83 -> -261300
B38: Equity Value | G38: =SUM(G34:G37) -> 458918.23
B39: No. of Shares | G39: =Statements!I53 -> 52614
B40: Price per Share | G40: =G38/G39 -> 8.7223597

Sheet Ratio Analysis
B2: =Dashboard!B2 -> Denny's Diner
B3: Ratio Analysis
B4: =Dashboard!B4 -> (In $ thousands, except per share amounts)
B5: Active Scenario | D5: =Dashboard!G13 -> Street
B6: Historicals / Forecast | G6: Historicals | J6: Forecast
B7: Month / Year (A/E) | G7: =Statements!G7 -> 44920 | H7: =EDATE(G7,12) -> 45285 | I7: =EDATE(H7,12) -> 45651 | J7: =EDATE(I7,12) -> 46016 | K7: =EDATE(J7,12) -> 46381 | L7: =EDATE(K7,12) -> 46746 | M7: =EDATE(L7,12) -> 47112 | N7: =EDATE(M7,12) -> 47477
B9: <-Back to dashboard

Sheet Report
A1: \

Sheet LBO_model
B2: =Dashboard!B2 -> Denny's Diner
B3: LBO Model
B4: =Dashboard!B4 -> (In $ thousands, except per share amounts)
Q5: Initial Cash Balance: | T5: =Y38 -> 2265.5068
B6: Denny's Diner LBO model as of FY 2025 | Q6: Minimum Cash Balance: | T6: -2000
B8: Transaction Assumptions | Q8: Income Statement | V8: Historical | Z8: Transaction Adjustments | AC8: Forecast
V9: 44920 | W9: 45285 | X9: 45651 | Y9: 46016 | Z9: Debit | AA9: Credit | AB9: 46016 | AC9: 46381 | AD9: 46746 | AE9: 47112 | AF9: 47477
B10: Current share price: | F10: 4.11 | H10: Equity purchase price: | L10: =F23 -> 328690.18
B11: Offer premium: | F11: 0.52 | H11: Enterprise value: | L11: =F29 -> 617931.21 | Q11: Revenue | V11: =Statements!G25 -> 456429 | W11: =Statements!H25 -> 463922 | X11: =Statements!I25 -> 452334 | Y11: =Statements!J25 -> 454702.27 | AC11: =Statements!K25 -> 464274.24 | AD11: =Statements!L25 -> 482759.04 | AE11: =Statements!M25 -> 503402.59 | AF11: =Statements!N25 -> 527996.41
B12: Offer price per share: | F12: =F10*(1+F11) -> 6.2472 | H12: EBITDA purchase multiple: | L12: =L11/(Comp_Comps!K22*1000) -> 8.7856105 | Q12: Costs of company restaurant sales | V12: =Statements!G31 -> 179458 | W12: =Statements!H31 -> 187599 | X12: =Statements!I31 -> 189744 | Y12: =Statements!J31 -> 187530.72 | AC12: =Statements!K31 -> 194258.49 | AD12: =Statements!L31 -> 206991.8 | AE12: =Statements!M31 -> 219482.07 | AF12: =Statements!N31 -> 235917.29
B13: Leverage ratio: | F13: 3 | H13: Debt required: | L13: =F13*(Comp_Comps!K22*1000) -> 211003.39
B14: Tax Rate: | F14: 0.26 | H14: Equity used: | L14: =L10-L13 -> 117686.79 | Q14: Costs of franchise and license revenue | V14: =Statements!G33 -> 135327 | W14: =Statements!H33 -> 122452 | X14: =Statements!I33 -> 120226 | Y14: =Statements!J33 -> 122250.35 | AC14: =Statements!K33 -> 122584.66 | AD14: =Statements!L33 -> 128099.44 | AE14: =Statements!M33 -> 133401.97 | AF14: =Statements!N33 -> 138979.76
H15: EBITDA exit multiple: | L15: 10 | Q15: General and administrative expenses | V15: =Statements!G34 -> 67173 | W15: =Statements!H34 -> 77770 | X15: =Statements!I34 -> 80197 | Y15: =Statements!J34 -> 74586.733 | AC15: =Statements!K34 -> 78766.623 | AD15: =Statements!L34 -> 82227.636 | AE15: =Statements!M34 -> 84574.678 | AF15: =Statements!N34 -> 89405.624
B16: Purchase price calculation | Q16: Depreciation and amortization | V16: =Statements!G35 -> 14862 | W16: =Statements!H35 -> 14385 | X16: =Statements!I35 -> 14857 | Y16: =Statements!J35 -> 13724.577 | AC16: =Statements!K35 -> 13914.684 | AD16: =Statements!L35 -> 14602.521 | AE16: =Statements!M35 -> 15365.381 | AF16: =Statements!N35 -> 16163.077
Q17: Depreciation of PP&E Write-Up: | AC17: =$L$65/$L$66 -> 1561.565 | AD17: =$L$65/$L$66 -> 1561.565 | AE17: =$L$65/$L$66 -> 1561.565 | AF17: =$L$65/$L$66 -> 1561.565
Q18: New Intangibles Amortization: | AC18: =$L$72/$L$73 -> 15713.465 | AD18: =$L$72/$L$73 -> 15713.465 | AE18: =$L$72/$L$73 -> 15713.465 | AF18: =$L$72/$L$73 -> 15713.465
Q19: Amortization of Financing Fees: | AC19: =$L$54/$F$76 -> 331.50509 | AD19: =$L$54/$F$76 -> 331.50509 | AE19: =$L$54/$F$76 -> 331.50509 | AF19: =$L$54/$F$76 -> 331.50509
B20: Basic shares outstanding: | F20: =Statements!J52 -> 52499 | H20: Advisory fee (%): | L20: 0.0025 | Q20: Goodwill impairment charges | V20: =Statements!G36 -> 0 | W20: =Statements!H36 -> 6363 | X20: =Statements!I36 -> 20 | Y20: =Statements!J36 -> 0 | AC20: =Statements!K36 -> 0 | AD20: =Statements!L36 -> 0 | AE20: =Statements!M36 -> 0 | AF20: =Statements!N36 -> 0
B21: Basic equity value: | F21: =F20*F12 -> 327971.75 | H21: Financing fee (%): | L21: 0.0075 | Q21: Operating (gains), losses and other charges, net | V21: =Statements!G37 -> -1005 | W21: =Statements!H37 -> 2530 | X21: =Statements!I37 -> 1974 | Y21: =Statements!J37 -> 0 | AC21: =Statements!K37 -> 0 | AD21: =Statements!L37 -> 0 | AE21: =Statements!M37 -> 0 | AF21: =Statements!N37 -> 0
B22: Diluted shares outstanding: | F22: =Statements!J53 -> 52614 | H22: Legal & Misc. fees (%): | L22: 0.005 | Q22: Total operating costs and expenses, net | V22: =Statements!G38 -> 395815 | W22: =Statements!H38 -> 411099 | X22: =Statements!I38 -> 407018 | Y22: =Statements!J38 -> 398092.38 | AC22: =SUM(AC14:AC21)+AC12 -> 427131 | AD22: =SUM(AD14:AD21)+AD12 -> 449527.93 | AE22: =SUM(AE14:AE21)+AE12 -> 470430.64 | AF22: =SUM(AF14:AF21)+AF12 -> 498072.28
B23: Diluted equity value: | F23: =F22*F12 -> 328690.18
B24: Less: Cash & cash equivalents: | F24: =-Statements!J59 -> -2265.5068 | Q24: Operating income | V24: =Statements!G40 -> 60614 | W24: =Statements!H40 -> 52823 | X24: =Statements!I40 -> 45316 | Y24: =Statements!J40 -> 56609.888 | AC24: =AC11-AC22 -> 37143.242 | AD24: =AD11-AD22 -> 33231.108 | AE24: =AE11-AE22 -> 32971.953 | AF24: =AF11-AF22 -> 29924.125
B25: Add: Debt: | F25: =Statements!J83 -> 211300
B26: Add: Minority interest: | F26: 0 | Q26: Interest expense, net | V26: =Statements!G41 -> 13769 | W26: =Statements!H41 -> 17597 | X26: =Statements!I41 -> 17974 | Y26: =Statements!J41 -> 16021.14 | AC26: =Statements!K41+(-AC150) -> 31630.4 | AD26: =Statements!L41+(-AD150) -> 26970.465 | AE26: =Statements!M41+(-AE150) -> 22975.306 | AF26: =Statements!N41+(-AF150) -> 19355.878
B27: Add: Preferred stock: | F27: 0 | Q27: Other nonoperating income, net | V27: =Statements!G42 -> -52585 | W27: =Statements!H42 -> 8288 | X27: =Statements!I42 -> -1907 | Y27: =Statements!J42 -> 0 | AC27: =Statements!K42 -> 0 | AD27: =Statements!L42 -> 0 | AE27: =Statements!M42 -> 0 | AF27: =Statements!N42 -> 0
B28: Add: Other liabilities: | F28: =Statements!J80+Statements!J79+Statements!J77 -> 80206.536 | Q28: Net income before income taxes | V28: =Statements!G43 -> 99430 | W28: =Statements!H43 -> 26938 | X28: =Statements!I43 -> 29249 | Y28: =Statements!J43 -> 40588.748 | AC28: =AC24-AC26-AC27 -> 5512.8422 | AD28: =AD24-AD26-AD27 -> 6260.6431 | AE28: =AE24-AE26-AE27 -> 9996.6473 | AF28: =AF24-AF26-AF27 -> 10568.248
B29: Enterprise value: | F29: =SUM(F23:F28) -> 617931.21 | Q29: Provision for income taxes | V29: =Statements!G44 -> 24718 | W29: =Statements!H44 -> 6993 | X29: =Statements!I44 -> 7678 | Y29: =Statements!J44 -> 10553.074 | AC29: =AC28*26% -> 1433.339 | AD29: =AD28*26% -> 1627.7672 | AE29: =AE28*26% -> 2599.1283 | AF29: =AF28*26% -> 2747.7444
Q30: Net income | V30: =Statements!G45 -> 74712 | W30: =Statements!H45 -> 19945 | X30: =Statements!I45 -> 21571 | Y30: =Statements!J45 -> 30035.673 | AC30: =AC28-AC29 -> 4079.5033 | AD30: =AD28-AD29 -> 4632.8759 | AE30: =AE28-AE29 -> 7397.519 | AF30: =AF28-AF29 -> 7820.5032
B32: Debt Assumptions
Q33: Balance Sheet | V33: Historical | Z33: Transaction Adjustments | AC33: Forecast
B34: Leverage ratio: | F34: =F13 -> 3 | H34: Debt Required: | L34: =L13 -> 211003.39 | V34: 44920 | W34: 45285 | X34: 45651 | Y34: 46016 | Z34: Debit | AA34: Credit | AB34: 46016 | AC34: 46381 | AD34: 46746 | AE34: 47112 | AF34: 47477
B35: Term Loan A (%): | F35: 0.5 | H35: Revolver: | L35: 10000
B36: Term Loan B (%): | F36: 0.25 | H36: Term Loan A : | L36: =$L$34*F35 -> 105501.7 | Q36: Assets
B37: Subordinated debt (%): | F37: 0.15 | H37: Term Loan B : | L37: =$L$34*F36 -> 52750.848 | Q37: Current assets:
B38: Mezzanine finance (%): | F38: 0.1 | H38: Subordinated debt : | L38: =$L$34*F37 -> 31650.509 | P38: * | Q38: Cash and cash equivalents | V38: =Statements!G59 -> 3523 | W38: =Statements!H59 -> 4893 | X38: =Statements!I59 -> 1698 | Y38: =Statements!J59 -> 2265.5068 | Z38: 0 | AA38: =F52 -> 265.50685 | AB38: =Y38+Z38-AA38 -> 2000 | AC38: =AC127 -> -29630.4 | AD38: =AD127 -> -24970.465 | AE38: =AE127 -> -20975.306 | AF38: =AF127 -> -17355.878
H39: Mezzanine finance : | L39: =$L$34*F38 -> 21100.339 | Q39: Investments | V39: =Statements!G60 -> 1746 | W39: =Statements!H60 -> 1281 | X39: =Statements!I60 -> 1106 | Y39: =Statements!J60 -> 1106 | Z39: 0 | AA39: 0 | AB39: =Y39+Z39-AA39 -> 1106 | AC39: =Statements!K60 -> 1106 | AD39: =Statements!L60 -> 1106 | AE39: =Statements!M60 -> 1106 | AF39: =Statements!N60 -> 1106
Q40: Receivables, net | V40: =Statements!G61 -> 25576 | W40: =Statements!H61 -> 21391 | X40: =Statements!I61 -> 24433 | Y40: =Statements!J61 -> 24560.923 | Z40: 0 | AA40: 0 | AB40: =Y40+Z40-AA40 -> 24560.923 | AC40: =Statements!K61 -> 25077.957 | AD40: =Statements!L61 -> 26076.42 | AE40: =Statements!M61 -> 27191.49 | AF40: =Statements!N61 -> 28519.935
B41: Interest rates (%) | H41: Principal repayment (%) | Q41: Inventories | V41: =Statements!G62 -> 5538 | W41: =Statements!H62 -> 2175 | X41: =Statements!I62 -> 1747 | Y41: =Statements!J62 -> 1726.622 | Z41: 0 | AA41: 0 | AB41: =Y41+Z41-AA41 -> 1726.622 | AC41: =Statements!K62 -> 1788.5656 | AD41: =Statements!L62 -> 1905.8029 | AE41: =Statements!M62 -> 2020.8026 | AF41: =Statements!N62 -> 2172.1241
B42: Revolver: | F42: SOFR + 150 | H42: Revolver: | L42: N/A | Q42: Assets held for sale | V42: =Statements!G63 -> 1403 | W42: =Statements!H63 -> 1455 | X42: =Statements!I63 -> 381 | Y42: =Statements!J63 -> 381 | Z42: 0 | AA42: 0 | AB42: =Y42+Z42-AA42 -> 381 | AC42: =Statements!K63 -> 381 | AD42: =Statements!L63 -> 381 | AE42: =Statements!M63 -> 381 | AF42: =Statements!N63 -> 381
B43: Term Loan A : | F43: SOFR + 300 | H43: Term Loan A : | L43: 0.1 | Q43: Prepaid and other current assets | V43: =Statements!G64 -> 12529 | W43: =Statements!H64 -> 12855 | X43: =Statements!I64 -> 10628 | Y43: =Statements!J64 -> 11921.591 | Z43: 0 | AA43: 0 | AB43: =Y43+Z43-AA43 -> 11921.591 | AC43: =Statements!K64 -> 11981.953 | AD43: =Statements!L64 -> 12153.023 | AE43: =Statements!M64 -> 12954.306 | AF43: =Statements!N64 -> 13501.838
B44: Term Loan B : | F44: SOFR + 400 | H44: Term Loan B : | L44: 0.02 | Q44: Total current assets | V44: =Statements!G65 -> 50315 | W44: =Statements!H65 -> 44050 | X44: =Statements!I65 -> 39993 | Y44: =Statements!J65 -> 41961.642 | AB44: =SUM(AB38:AB43) -> 41696.136 | AC44: =SUM(AC38:AC43) -> 10705.076 | AD44: =SUM(AD38:AD43) -> 16651.781 | AE44: =SUM(AE38:AE43) -> 22678.293 | AF44: =SUM(AF38:AF43) -> 28325.019
B45: Subordinated debt : | F45: 0.12 | H45: Subordinated debt : | L45: 0 | P45: * | Q45: Property, net of accumulated depreciation | V45: =Statements!G66 -> 94469 | W45: =Statements!H66 -> 93494 | X45: =Statements!I66 -> 111417 | Y45: =Statements!J66 -> 104104.34 | Z45: =L65 -> 12492.52 | AA45: 0 | AB45: =Y45+Z45-AA45 -> 116596.86 | AC45: =AB45-Schedule!K27-LBO_model!AC96-LBO_model!AC111 -> 116985.33 | AD45: =AC45-Schedule!L27-LBO_model!AD96-LBO_model!AD111 -> 117551.88 | AE45: =AD45-Schedule!M27-LBO_model!AE96-LBO_model!AE111 -> 118172.45 | AF45: =AE45-Schedule!N27-LBO_model!AF96-LBO_model!AF111 -> 119023.56
B46: Mezzanine finance : | F46: 0.15 | H46: Mezzanine finance : | L46: 0 | P46: * | Q46: Financing lease right-of-use assets, net | V46: =Statements!G67 -> 6499 | W46: =Statements!H67 -> 6098 | X46: =Statements!I67 -> 6200 | Y46: =Statements!J67 -> 6200 | Z46: 0 | AA46: 0 | AB46: =Y46+Z46-AA46 -> 6200 | AC46: =Statements!K67 -> 6200 | AD46: =Statements!L67 -> 6200 | AE46: =Statements!M67 -> 6200 | AF46: =Statements!N67 -> 6200
P47: * | Q47: Operating lease right-of-use assets, net | V47: =Statements!G68 -> 126065 | W47: =Statements!H68 -> 116795 | X47: =Statements!I68 -> 124738 | Y47: =Statements!J68 -> 124738 | Z47: 0 | AA47: 0 | AB47: =Y47+Z47-AA47 -> 124738 | AC47: =Statements!K68 -> 124738 | AD47: =Statements!L68 -> 124738 | AE47: =Statements!M68 -> 124738 | AF47: =Statements!N68 -> 124738
P48: * | Q48: Goodwill | V48: =Statements!G69 -> 72740 | W48: =Statements!H69 -> 65908 | X48: =Statements!I69 -> 66357 | Y48: =Statements!J69 -> 66357 | Z48: =F73 -> 325452.34 | AA48: =Y48 -> 66357 | AB48: =Y48+Z48-AA48 -> 325452.34 | AC48: =AB48 -> 325452.34 | AD48: =AC48 -> 325452.34 | AE48: =AD48 -> 325452.34 | AF48: =AE48 -> 325452.34
B49: Sources & Uses | P49: * | Q49: Intangible assets, net | V49: =Statements!G70 -> 95034 | W49: =Statements!H70 -> 93428 | X49: =Statements!I70 -> 91739 | Y49: =Statements!J70 -> 91669.663 | Z49: =L72 -> 78567.325 | AA49: 0 | AB49: =Y49+Z49-AA49 -> 170236.99 | AC49: =AB49-Schedule!K45-LBO_model!AC97 -> 152618.06 | AD49: =AC49-Schedule!L45-LBO_model!AD97 -> 134695.8 | AE49: =AD49-Schedule!M45-LBO_model!AE97 -> 116573.72 | AF49: =AE49-Schedule!N45-LBO_model!AF97 -> 98163.243
Q50: Deferred financing costs, net | V50: =Statements!G71 -> 2337 | W50: =Statements!H71 -> 1702 | X50: =Statements!I71 -> 1066 | Y50: =Statements!J71 -> 1066 | Z50: 0 | AA50: 0 | AB50: =Y50+Z50-AA50 -> 1066 | AC50: =Statements!K71 -> 1066 | AD50: =Statements!L71 -> 1066 | AE50: =Statements!M71 -> 1066 | AF50: =Statements!N71 -> 1066
B51: Sources | H51: Uses | Q51: Other noncurrent assets | V51: =Statements!G72 -> 50876 | W51: =Statements!H72 -> 43343 | X51: =Statements!I72 -> 54764 | Y51: =Statements!J72 -> 49405.293 | Z51: 0 | AA51: 0 | AB51: =Y51+Z51-AA51 -> 49405.293 | AC51: =Statements!K72 -> 50010.28 | AD51: =Statements!L72 -> 54300.914 | AE51: =Statements!M72 -> 55181.589 | AF51: =Statements!N72 -> 58046.991
B52: Excess cash: | F52: =T5+T6 -> 265.50685 | H52: Equity Value of Company: | L52: =L10 -> 328690.18 | P52: * | Q52: Capitalised Financing fees | V52: 0 | W52: 0 | X52: 0 | Y52: 0 | Z52: =L54 -> 1657.5254 | AA52: 0 | AB52: =Y52+Z52-AA52 -> 1657.5254 | AC52: =AB52-AC98 -> 1326.0204 | AD52: =AC52-AD98 -> 994.51527 | AE52: =AD52-AE98 -> 663.01018 | AF52: =AE52-AF98 -> 331.50509
B53: Term Loan A: | F53: =L36 -> 105501.7 | H53: Advisory fee : | L53: =L20*L10 -> 821.72545 | Q53: Total assets | V53: =SUM(V45:V52)+V44 -> 498335 | W53: =SUM(W45:W52)+W44 -> 464818 | X53: =SUM(X45:X52)+X44 -> 496274 | Y53: =SUM(Y45:Y52)+Y44 -> 485501.93 | AB53: =SUM(AB45:AB52)+AB44 -> 837049.14 | AC53: =SUM(AC45:AC52)+AC44 -> 789101.1 | AD53: =SUM(AD45:AD52)+AD44 -> 781651.23 | AE53: =SUM(AE45:AE52)+AE44 -> 770725.41 | AF53: =SUM(AF45:AF52)+AF44 -> 761346.66
B54: Term Loan B : | F54: =L37 -> 52750.848 | H54: Capitalised Financing fee : | L54: =(L34+L35)*L21 -> 1657.5254
B55: Subordinated debt : | F55: =L38 -> 31650.509 | H55: Legal & Misc. fees : | L55: =L22*L10 -> 1643.4509 | Q55: Liabilities
B56: Mezzanine finance : | F56: =L39 -> 21100.339 | Q56: Current liabilities:
B57: Investor equity: | F57: =L58-SUM(F52:F56) -> 121543.98 | Q57: Current finance lease liabilities | V57: =Statements!G77 -> 1683 | W57: =Statements!H77 -> 1383 | X57: =Statements!I77 -> 1284 | Y57: =Statements!J77 -> 1284 | Z57: 0 | AA57: 0 | AB57: =Y57-Z57+AA57 -> 1284 | AC57: =Statements!K77 -> 1284 | AD57: =Statements!L77 -> 1284 | AE57: =Statements!M77 -> 1284 | AF57: =Statements!N77 -> 1284
B58: Total Sources | F58: =SUM(F52:F57) -> 332812.88 | H58: Total Uses | L58: =SUM(L52:L57) -> 332812.88 | Q58: Current operating lease liabilities | V58: =Statements!G78 -> 15310 | W58: =Statements!H78 -> 14779 | X58: =Statements!I78 -> 15487 | Y58: =Statements!J78 -> 15487 | Z58: 0 | AA58: 0 | AB58: =Y58-Z58+AA58 -> 15487 | AC58: =Statements!K78 -> 15487 | AD58: =Statements!L78 -> 15487 | AE58: =Statements!M78 -> 15487 | AF58: =Statements!N78 -> 15487
Q59: Accounts payable | V59: =Statements!G79 -> 19896 | W59: =Statements!H79 -> 24070 | X59: =Statements!I79 -> 19985 | Y59: =Statements!J79 -> 19751.883 | Z59: 0 | AA59: 0 | AB59: =Y59-Z59+AA59 -> 19751.883 | AC59: =Statements!K79 -> 20460.494 | AD59: =Statements!L79 -> 21801.644 | AE59: =Statements!M79 -> 23117.195 | AF59: =Statements!N79 -> 24848.254
Q60: Other current liabilities | V60: =Statements!G80 -> 56762 | W60: =Statements!H80 -> 63068 | X60: =Statements!I80 -> 58842 | Y60: =Statements!J80 -> 59170.653 | Z60: 0 | AA60: 0 | AB60: =Y60-Z60+AA60 -> 59170.653 | AC60: =Statements!K80 -> 61309.131 | AD60: =Statements!L80 -> 63123.888 | AE60: =Statements!M80 -> 65935.798 | AF60: =Statements!N80 -> 69306.65
A61: * | B61: Goodwill Creation & Balance sheet Adjustments | Q61: Total current liabilities | V61: =Statements!G81 -> 93651 | W61: =Statements!H81 -> 103300 | X61: =Statements!I81 -> 95598 | Y61: =Statements!J81 -> 95693.536 | AB61: =SUM(AB57:AB60) -> 95693.536 | AC61: =SUM(AC57:AC60) -> 98540.625 | AD61: =SUM(AD57:AD60) -> 101696.53 | AE61: =SUM(AE57:AE60) -> 105823.99 | AF61: =SUM(AF57:AF60) -> 110925.9
P62: * | Q62: Revolver | V62: =Statements!G82 -> 0 | W62: =Statements!H82 -> 0 | X62: =Statements!I82 -> 0 | Y62: =Statements!J82 -> 0 | Z62: 0 | AA62: 0 | AB62: =Y62-Z62+AA62 -> 0 | AC62: =AB62+AC115 -> 0 | AD62: =AC62+AD115 -> 21840.734 | AE62: =AD62+AE115 -> 34910.478 | AF62: =AE62+AF115 -> 47573.544
B63: Goodwill calculation | H63: Fixed asset-write up | Q63: Long-term debt (Existing) | V63: =Statements!G83 -> 261500 | W63: =Statements!H83 -> 255500 | X63: =Statements!I83 -> 261300 | Y63: =Statements!J83 -> 211300 | Z63: 0 | AA63: 0 | AB63: =Y63-Z63+AA63 -> 211300 | AC63: =AB63+AC120 -> 171300 | AD63: =AC63+AD120 -> 131300 | AE63: =AD63+AE120 -> 91300 | AF63: =AE63+AF120 -> 51300
B64: Equity purchase value: | F64: =L10 -> 328690.18 | H64: PP&E write-up (%): | L64: 0.12 | P64: * | Q64: Term Loan A: | V64: 0 | W64: 0 | X64: 0 | Y64: 0 | Z64: 0 | AA64: =F53 -> 105501.7 | AB64: =Y64-Z64+AA64 -> 105501.7 | AC64: =AB64+AC116 -> 78669.443 | AD64: =AC64+AD116 -> 68119.274 | AE64: =AD64+AE116 -> 57569.104 | AF64: =AE64+AF116 -> 47018.935
B65: Less: Seller book value: | F65: =-Y84 -> -2210.5536 | H65: PP&E write-up amount: | L65: =L64*Y45 -> 12492.52 | P65: * | Q65: Term Loan B : | V65: 0 | W65: 0 | X65: 0 | Y65: 0 | Z65: 0 | AA65: =F54 -> 52750.848 | AB65: =Y65-Z65+AA65 -> 52750.848 | AC65: =AB65+AC117 -> 51695.831 | AD65: =AC65+AD117 -> 50640.814 | AE65: =AD65+AE117 -> 49585.797 | AF65: =AE65+AF117 -> 48530.78
B66: Add: Write-off of existing goodwill: | F66: =Y48 -> 66357 | H66: Depreciation period (Years): | L66: 8 | P66: * | Q66: Subordinated debt : | V66: 0 | W66: 0 | X66: 0 | Y66: 0 | Z66: 0 | AA66: =F55 -> 31650.509 | AB66: =Y66-Z66+AA66 -> 31650.509 | AC66: =AB66+AC118 -> 31650.509 | AD66: =AC66+AD118 -> 31650.509 | AE66: =AD66+AE118 -> 31650.509 | AF66: =AE66+AF118 -> 31650.509
B67: Total allocable purchase premium: | F67: =SUM(F64:F66) -> 392836.63 | P67: * | Q67: Mezzanine finance : | V67: 0 | W67: 0 | X67: 0 | Y67: 0 | Z67: 0 | AA67: =F56 -> 21100.339 | AB67: =Y67-Z67+AA67 -> 21100.339 | AC67: =AB67+AC119+AC99 -> 24522.016 | AD67: =AC67+AD119+AD99 -> 28498.559 | AE67: =AD67+AE119+AE99 -> 33119.947 | AF67: =AE67+AF119+AF99 -> 38490.749
P68: * | Q68: Deferred tax liability | V68: 0 | W68: 0 | X68: 0 | Y68: 0 | Z68: 0 | AA68: =L76 -> 23675.56 | AB68: =Y68-Z68+AA68 -> 23675.56 | AC68: =AB68 -> 23675.56 | AD68: =AC68 -> 23675.56 | AE68: =AD68 -> 23675.56 | AF68: =AE68 -> 23675.56
B69: Less: Write-up of PP&E: | F69: =-L65 -> -12492.52 | H69: Intangible asset-write up | Q69: Noncurrent finance lease liabilities | V69: =Statements!G84 -> 9555 | W69: =Statements!H84 -> 9150 | X69: =Statements!I84 -> 9284 | Y69: =Statements!J84 -> 9284 | Z69: 0 | AA69: 0 | AB69: =Y69-Z69+AA69 -> 9284 | AC69: =Statements!K84 -> 9284 | AD69: =Statements!L84 -> 9284 | AE69: =Statements!M84 -> 9284 | AF69: =Statements!N84 -> 9284
B70: Less: Write-up of Intangibles: | F70: =-L72 -> -78567.325 | H70: Purchase price to allocate: | L70: =F67 -> 392836.63 | Q70: Noncurrent operating lease liabilities | V70: =Statements!G85 -> 123404 | W70: =Statements!H85 -> 114451 | X70: =Statements!I85 -> 120841 | Y70: =Statements!J85 -> 120841 | Z70: 0 | AA70: 0 | AB70: =Y70-Z70+AA70 -> 120841 | AC70: =Statements!K85 -> 120841 | AD70: =Statements!L85 -> 120841 | AE70: =Statements!M85 -> 120841 | AF70: =Statements!N85 -> 120841
B71: Less: Write-up of DTL: | F71: 0 | H71: % allocated to intangibles: | L71: 0.2 | Q71: Liability for insurance claims, less current portion | V71: =Statements!G86 -> 7324 | W71: =Statements!H86 -> 6929 | X71: =Statements!I86 -> 5866 | Y71: =Statements!J86 -> 5866 | Z71: 0 | AA71: 0 | AB71: =Y71-Z71+AA71 -> 5866 | AC71: =Statements!K86 -> 5866 | AD71: =Statements!L86 -> 5866 | AE71: =Statements!M86 -> 5866 | AF71: =Statements!N86 -> 5866
B72: Add: New Deferred tax liabilities: | F72: =L76 -> 23675.56 | H72: Intangilbes write-up amount: | L72: =L70*L71 -> 78567.325 | Q72: Deferred income taxes, net | V72: =Statements!G87 -> 7419 | W72: =Statements!H87 -> 6582 | X72: =Statements!I87 -> 9964 | Y72: =Statements!J87 -> 9964 | Z72: 0 | AA72: 0 | AB72: =Y72-Z72+AA72 -> 9964 | AC72: =Statements!K87 -> 9964 | AD72: =Statements!L87 -> 9964 | AE72: =Statements!M87 -> 9964 | AF72: =Statements!N87 -> 9964
B73: Total goodwill created: | F73: =F67+SUM(F69:F72) -> 325452.34 | H73: Amortization period (Years): | L73: 5 | Q73: Other noncurrent liabilities | V73: =Statements!G88 -> 32598 | W73: =Statements!H88 -> 31592 | X73: =Statements!I88 -> 27446 | Y73: =Statements!J88 -> 30342.844 | Z73: 0 | AA73: 0 | AB73: =Y73-Z73+AA73 -> 30342.844 | AC73: =Statements!K88 -> 30256.024 | AD73: =Statements!L88 -> 30989.279 | AE73: =Statements!M88 -> 32904.355 | AF73: =Statements!N88 -> 34271.253
Q74: Total long-term liabilities | V74: =Statements!G89 -> 441800 | W74: =Statements!H89 -> 424204 | X74: =Statements!I89 -> 434701 | Y74: =Statements!J89 -> 387597.84 | AB74: =SUM(AB62:AB73) -> 622276.8 | AC74: =SUM(AC62:AC73) -> 557724.38 | AD74: =SUM(AD62:AD73) -> 532669.73 | AE74: =SUM(AE62:AE73) -> 500670.75 | AF74: =SUM(AF62:AF73) -> 468466.33
Q75: Total liabilities | V75: =Statements!G90 -> 535451 | W75: =Statements!H90 -> 527504 | X75: =Statements!I90 -> 530299 | Y75: =Statements!J90 -> 483291.38 | AB75: =AB74+AB61 -> 717970.33 | AC75: =AC74+AC61 -> 656265.01 | AD75: =AD74+AD61 -> 634366.26 | AE75: =AE74+AE61 -> 606494.74 | AF75: =AF74+AF61 -> 579392.23
B76: Financing fees amortization period: | F76: 5 | H76: New deferred tax liability: | L76: =(L72+L65)*F14 -> 23675.56
Q77: Shareholders' deficit
Q78: Common Stock | V78: =Statements!G93 -> 650 | W78: =Statements!H93 -> 529 | X78: =Statements!I93 -> 513 | Y78: =Statements!J93 -> 513 | Z78: =Y78 -> 513 | AB78: =Y78-Z78+AA78 -> 0 | AC78: =AB78 -> 0 | AD78: =AC78 -> 0 | AE78: =AD78 -> 0 | AF78: =AE78 -> 0
A79: * | B79: Investor Returns | Q79: Paid-in capital | V79: =Statements!G94 -> 142136 | W79: =Statements!H94 -> 6688 | X79: =Statements!I94 -> 0 | Y79: =Statements!J94 -> 7699.8804 | Z79: =Y79 -> 7699.8804 | AB79: =Y79-Z79+AA79 -> 0 | AC79: =AB79+AC100 -> 9677.7862 | AD79: =AC79+AD100 -> 19493.788 | AE79: =AD79+AE100 -> 29041.958 | AF79: =AE79+AF100 -> 38945.215 | AG79: *add share based compensation
H80: 46016 | I80: 46381 | J80: 46746 | K80: 47112 | L80: 47477 | Q80: Deficit | V80: =Statements!G95 -> -41729 | W80: =Statements!H95 -> -21784 | X80: =Statements!I95 -> -2499 | Y80: =Statements!J95 -> 26036.673 | Z80: =Y80+L53+L55 -> 28501.85 | AB80: =Y80-Z80+AA80 -> -2465.1764 | AC80: =AB80+AC30 -> 1614.3269 | AD80: =AC80+AD30 -> 6247.2028 | AE80: =AD80+AE30 -> 13644.722 | AF80: =AE80+AF30 -> 21465.225 | AG80: *add net income and less dividends paid
Q81: Accumulated other comprehensive loss, net | V81: =Statements!G96 -> -42697 | W81: =Statements!H96 -> -41659 | X81: =Statements!I96 -> -32039 | Y81: =Statements!J96 -> -32039 | Z81: =Y81 -> -32039 | AB81: =Y81-Z81+AA81 -> 0 | AC81: =AB81 -> 0 | AD81: =AC81 -> 0 | AE81: =AD81 -> 0 | AF81: =AE81 -> 0
B82: EBITDA | H82: =Y24+Y16+Y17+Y18+Y19 -> 70334.464 | L82: =AF24+AF17+AF16+AF18+AF19 -> 63693.738 | Q82: Treasury stock | V82: =Statements!G97 -> -95476 | W82: =Statements!H97 -> -6460 | X82: =Statements!I97 -> 0 | Y82: =Statements!J97 -> 0 | Z82: =Y82 -> 0 | AB82: =Y82-Z82+AA82 -> 0 | AC82: =Statements!K97 -> 0 | AD82: =Statements!L97 -> 0 | AE82: =Statements!M97 -> 0 | AF82: =Statements!N97 -> 0
B83: EBITDA Multiple | H83: =L12 -> 8.7856105 | L83: =L15 -> 10 | P83: * | Q83: Sponsor Common Equity | V83: 0 | W83: 0 | X83: 0 | Y83: 0 | Z83: 0 | AA83: =F57 -> 121543.98 | AB83: =Y83-Z83+AA83 -> 121543.98 | AC83: =AB83 -> 121543.98 | AD83: =AC83 -> 121543.98 | AE83: =AD83 -> 121543.98 | AF83: =AE83 -> 121543.98
B84: Enterprise value | H84: =L11 -> 617931.21 | L84: =L83*L82 -> 636937.38 | Q84: Total shareholders' deficit | V84: =Statements!G98 -> -37116 | W84: =Statements!H98 -> -62686 | X84: =Statements!I98 -> -34025 | Y84: =Statements!J98 -> 2210.5536 | AB84: =SUM(AB78:AB83) -> 119078.81 | AC84: =SUM(AC78:AC83) -> 132836.1 | AD84: =SUM(AD78:AD83) -> 147284.97 | AE84: =SUM(AE78:AE83) -> 164230.66 | AF84: =SUM(AF78:AF83) -> 181954.42
B85: Investor return | H85: =-F57 -> -121543.98 | I85: 0 | J85: 0 | K85: 0 | L85: =L84-AF62-AF63-AF64-AF65-AF66-AF67+AF38+AF39 -> 356122.98 | Q85: Total liabilities and shareholders' deficit | V85: =Statements!G99 -> 498335 | W85: =Statements!H99 -> 464818 | X85: =Statements!I99 -> 496274 | Y85: =Statements!J99 -> 485501.93 | AB85: =AB75+AB84 -> 837049.14 | AC85: =AC84+AC75 -> 789101.1 | AD85: =AD84+AD75 -> 781651.23 | AE85: =AE84+AE75 -> 770725.41 | AF85: =AF84+AF75 -> 761346.66
B87: IRR: | H87: =IRR(H85:L85) -> 0.308328 | R87: Check | V87: =IF(V85=V53,TRUE,V53-V85) -> TRUE | W87: =IF(W85=W53,TRUE,W53-W85) -> TRUE | X87: =IF(X85=X53,TRUE,X53-X85) -> TRUE | Y87: =IF(Y85=Y53,TRUE,Y53-Y85) -> TRUE | AB87: =IF(AB85=AB53,TRUE,AB53-AB85) -> TRUE | AC87: =IF(AC85=AC53,TRUE,AC53-AC85) -> TRUE | AD87: =IF(AD85=AD53,TRUE,AD53-AD85) -> 3.4924597e-09 | AE87: =IF(AE85=AE53,TRUE,AE53-AE85) -> -2.3317989e-07 | AF87: =IF(AF85=AF53,TRUE,AF53-AF85) -> -5.2921358e-05
B90: Sensitivity Analysis - 5-Year IRR and Purchase Premium vs. Exit Multiple | Q90: Cash Flow Statement | V90: Historical | Z90: Transaction Adjustments | AC90: Forecast
V91: 44920 | W91: 45285 | X91: 45651 | Y91: 46016 | Z91: Debit | AA91: Credit | AB91: 46016 | AC91: 46381 | AD91: 46746 | AE91: 47112 | AF91: 47477
E92: Exit Multiple
D93: =H87 -> 0.308328 | E93: 6 | F93: =E93+1 -> 7 | G93: =F93+1 -> 8 | H93: =G93+1 -> 9 | I93: =H93+1 -> 10 | J93: =I93+1 -> 11 | K93: =J93+1 -> 12 | L93: =K93+1 -> 13 | M93: =L93+1 -> 14 | Q93: Net income | AC93: =AC30 -> 4079.5033 | AD93: =AD30 -> 4632.8759 | AE93: =AE30 -> 7397.519 | AF93: =AF30 -> 7820.5032
B94: Purchase Premium / Per Share Price | C94: =$F$10*(1+D94) -> 6.987 | D94: =D95+5% -> 0.7 | E94: -0.10540459 | F94: 0.0090479882 | G94: 0.094090534 | H94: 0.16294473 | I94: 0.22136965 | J94: 0.27244095 | K94: 0.31801189 | L94: 0.35929312 | M94: 0.39712286 | Q94: Add/Less: Non-cash items
C95: =$F$10*(1+D95) -> 6.7815 | D95: =D96+5% -> 0.65 | E95: -0.090567238 | F95: 0.026212393 | G95: 0.11290918 | H95: 0.18307272 | I95: 0.24259338 | J95: 0.29461358 | K95: 0.34102552 | L95: 0.38306471 | M95: 0.42158627 | Q95: Depreciation & Amortization | AC95: =AC16 -> 13914.684 | AD95: =AD16 -> 14602.521 | AE95: =AE16 -> 15365.381 | AF95: =AF16 -> 16163.077
C96: =$F$10*(1+D96) -> 6.576 | D96: =D97+5% -> 0.6 | E96: -0.074263057 | F96: 0.045049948 | G96: 0.13355065 | H96: 0.20514333 | I96: 0.26586073 | J96: 0.31891773 | K96: 0.36624887 | L96: 0.4091167 | M96: 0.44839472 | Q96: Depreciation of PP&E Write-Up: | AC96: =AC17 -> 1561.565 | AD96: =AD17 -> 1561.565 | AE96: =AE17 -> 1561.565 | AF96: =AF17 -> 1561.565
C97: =$F$10*(1+D97) -> 6.3705 | D97: =D98+5% -> 0.55 | E97: -0.05621812 | F97: 0.065872319 | G97: 0.15635413 | H97: 0.22951788 | I97: 0.29155166 | J97: 0.34574963 | K97: 0.39409264 | L97: 0.43787286 | M97: 0.47798399 | Q97: New Intangibles Amortization: | AC97: =AC18 -> 15713.465 | AD97: =AD18 -> 15713.465 | AE97: =AE18 -> 15713.465 | AF97: =AF18 -> 15713.465
C98: =$F$10*(1+D98) -> 6.165 | D98: =D99+5% -> 0.5 | E98: -0.036078231 | F98: 0.089082428 | G98: 0.18175812 | H98: 0.25666341 | I98: 0.32015735 | J98: 0.37562145 | K98: 0.4250877 | L98: 0.46988099 | M98: 0.51091731 | Q98: Amortization of Financing Fees: | AC98: =AC19 -> 331.50509 | AD98: =AD19 -> 331.50509 | AE98: =AE19 -> 331.50509 | AF98: =AF19 -> 331.50509
C99: =$F$10*(1+D99) -> 5.9595 | D99: =D100+5% -> 0.45 | E99: -0.013375132 | F99: 0.11521285 | G99: 0.21034218 | H99: 0.28719722 | I99: 0.35232693 | J99: 0.40921007 | K99: 0.45993563 | L99: 0.50586499 | M99: 0.54793906 | Q99: Accrual of Mezzanine: | AC99: =-AC148 -> 3421.6766 | AD99: =-AD148 -> 3976.5431 | AE99: =-AE148 -> 4621.388 | AF99: =-AF148 -> 5370.8022
C100: =$F$10*(1+D100) -> 5.754 | D100: =D101+5% -> 0.4 | E100: 0.012526797 | F100: 0.1449864 | G100: 0.24289282 | H100: 0.32195694 | I100: 0.38894124 | J100: 0.44743399 | K100: 0.49958844 | L100: 0.54680719 | M100: 0.59005928 | Q100: Share-based compensation | AC100: =Statements!K108 -> 9677.7862 | AD100: =Statements!L108 -> 9816.0015 | AE100: =Statements!M108 -> 9548.1705 | AF100: =Statements!N108 -> 9903.2566
C101: =$F$10*(1+D101) -> 5.5485 | D101: =D102+5% -> 0.35 | E101: 0.042518416 | F101: 0.17941593 | G101: 0.28051208 | H101: 0.36211628 | I101: 0.43123449 | J101: 0.49158012 | K101: 0.54537998 | L101: 0.59408388 | M101: 0.63869312 | Q101: Interest expenses | AC101: =AC26 -> 31630.4 | AD101: =AD26 -> 26970.465 | AE101: =AE26 -> 22975.306 | AF101: =AF26 -> 19355.878
C102: =$F$10*(1+D102) -> 5.343 | D102: =D103+5% -> 0.3 | E102: 0.077898805 | F102: 0.21997822 | G102: 0.32480666 | H102: 0.40938629 | I102: 0.48100587 | J102: 0.54352448 | K102: 0.59925467 | L102: 0.64970134 | M102: 0.69590346 | Q102: Change in working capital
C103: =$F$10*(1+D103) -> 5.1375 | D103: 0.25 | E103: 0.12066026 | F103: 0.26893764 | G103: 0.37823995 | H103: 0.46639031 | I103: 0.54101382 | J103: 0.60614323 | K103: 0.66419349 | L103: 0.71673534 | M103: 0.76485286 | Q103: Receivables | AC103: =AB40-AC40 -> -517.03396 | AD103: =AC40-AD40 -> -998.46364 | AE103: =AD40-AE40 -> -1115.0697 | AF103: =AE40-AF40 -> -1328.4448
Q104: Inventories | AC104: =AB41-AC41 -> -61.943575 | AD104: =AC41-AD41 -> -117.23738 | AE104: =AD41-AE41 -> -114.99968 | AF104: =AE41-AF41 -> -151.32143
B105: Sensitivity Analysis - 5-Year IRR and Purchase Premium vs. Leverage ratio | Q105: Prepaid and other current assets | AC105: =AB43-AC43 -> -60.362663 | AD105: =AC43-AD43 -> -171.0691 | AE105: =AD43-AE43 -> -801.28353 | AF105: =AE43-AF43 -> -547.53177
Q106: Accounts payable | AC106: =AC59-AB59 -> 708.61038 | AD106: =AD59-AC59 -> 1341.15 | AE106: =AE59-AD59 -> 1315.5515 | AF106: =AF59-AE59 -> 1731.0583
...

Sheet Equity Report
H1: SEQUEIRA CAPITAL INVESTMENTS
B2: Date | E2: COUNTRY | SECTOR | EQUITY RESEARCH
B4: Company Name
B5: NSE: | BSE: | F5: s
B8: Model Date: | Last Historical Year: FY 25 | Forecast Horizon: FY 26-FY 30 | I8: Eldric Gregory Sequeira
I9: seqcapin@gmaco | 91+ 11111111111
I14: Recommendation
I15: Recommendation
I16: DCF fair value
I17: WACC
I18: Terminal Growth rate
I19: Upside / (Downside)
I21: Key Data - INFO
I22: CMP
I23: Market Cap
I24: Free float
I25: Shares outstanding
... I28: INR/US
